{
    "0_300_2330b": {
        "0": {
            "left": 0,
            "top": 614,
            "right": 45,
            "bottom": 997
        },
        "1": {
            "left": 0,
            "top": 614,
            "right": 49,
            "bottom": 998
        },
        "2": {
            "left": 0,
            "top": 614,
            "right": 54,
            "bottom": 1000
        },
        "3": {
            "left": 0,
            "top": 612,
            "right": 59,
            "bottom": 1002
        },
        "4": {
            "left": 0,
            "top": 612,
            "right": 63,
            "bottom": 1003
        },
        "5": {
            "left": 0,
            "top": 612,
            "right": 67,
            "bottom": 1004
        },
        "6": {
            "left": 0,
            "top": 610,
            "right": 72,
            "bottom": 1006
        },
        "7": {
            "left": 0,
            "top": 610,
            "right": 76,
            "bottom": 1007
        },
        "8": {
            "left": 0,
            "top": 609,
            "right": 81,
            "bottom": 1009
        },
        "9": {
            "left": 0,
            "top": 608,
            "right": 85,
            "bottom": 1011
        },
        "10": {
            "left": 0,
            "top": 607,
            "right": 91,
            "bottom": 1012
        },
        "11": {
            "left": 0,
            "top": 606,
            "right": 94,
            "bottom": 1014
        },
        "12": {
            "left": 0,
            "top": 606,
            "right": 98,
            "bottom": 1015
        },
        "13": {
            "left": 0,
            "top": 605,
            "right": 104,
            "bottom": 1017
        },
        "14": {
            "left": 0,
            "top": 604,
            "right": 109,
            "bottom": 1018
        },
        "15": {
            "left": 0,
            "top": 603,
            "right": 113,
            "bottom": 1020
        },
        "16": {
            "left": 0,
            "top": 604,
            "right": 118,
            "bottom": 1022
        },
        "17": {
            "left": 0,
            "top": 604,
            "right": 120,
            "bottom": 1023
        },
        "18": {
            "left": 0,
            "top": 605,
            "right": 126,
            "bottom": 1024
        },
        "19": {
            "left": 0,
            "top": 604,
            "right": 130,
            "bottom": 1026
        },
        "20": {
            "left": 0,
            "top": 605,
            "right": 133,
            "bottom": 1028
        },
        "21": {
            "left": 0,
            "top": 605,
            "right": 137,
            "bottom": 1030
        },
        "22": {
            "left": 0,
            "top": 606,
            "right": 143,
            "bottom": 1031
        },
        "23": {
            "left": 0,
            "top": 607,
            "right": 145,
            "bottom": 1033
        },
        "24": {
            "left": 1,
            "top": 606,
            "right": 150,
            "bottom": 1035
        },
        "25": {
            "left": 2,
            "top": 607,
            "right": 154,
            "bottom": 1037
        },
        "26": {
            "left": 5,
            "top": 607,
            "right": 158,
            "bottom": 1037
        },
        "27": {
            "left": 7,
            "top": 608,
            "right": 160,
            "bottom": 1039
        },
        "28": {
            "left": 10,
            "top": 607,
            "right": 164,
            "bottom": 1041
        },
        "29": {
            "left": 12,
            "top": 608,
            "right": 168,
            "bottom": 1043
        },
        "30": {
            "left": 15,
            "top": 609,
            "right": 171,
            "bottom": 1044
        },
        "31": {
            "left": 16,
            "top": 606,
            "right": 174,
            "bottom": 1042
        },
        "32": {
            "left": 18,
            "top": 603,
            "right": 176,
            "bottom": 1042
        },
        "33": {
            "left": 20,
            "top": 601,
            "right": 178,
            "bottom": 1040
        },
        "34": {
            "left": 23,
            "top": 600,
            "right": 182,
            "bottom": 1040
        },
        "35": {
            "left": 25,
            "top": 599,
            "right": 184,
            "bottom": 1041
        },
        "36": {
            "left": 29,
            "top": 600,
            "right": 188,
            "bottom": 1042
        },
        "37": {
            "left": 33,
            "top": 601,
            "right": 192,
            "bottom": 1044
        },
        "38": {
            "left": 37,
            "top": 601,
            "right": 198,
            "bottom": 1046
        },
        "39": {
            "left": 42,
            "top": 602,
            "right": 203,
            "bottom": 1047
        },
        "40": {
            "left": 46,
            "top": 602,
            "right": 207,
            "bottom": 1049
        },
        "41": {
            "left": 50,
            "top": 602,
            "right": 213,
            "bottom": 1049
        },
        "42": {
            "left": 55,
            "top": 602,
            "right": 218,
            "bottom": 1050
        },
        "43": {
            "left": 60,
            "top": 600,
            "right": 223,
            "bottom": 1051
        },
        "44": {
            "left": 65,
            "top": 600,
            "right": 230,
            "bottom": 1051
        },
        "45": {
            "left": 70,
            "top": 600,
            "right": 235,
            "bottom": 1052
        },
        "46": {
            "left": 75,
            "top": 601,
            "right": 240,
            "bottom": 1054
        },
        "47": {
            "left": 80,
            "top": 601,
            "right": 246,
            "bottom": 1054
        },
        "48": {
            "left": 86,
            "top": 601,
            "right": 252,
            "bottom": 1057
        },
        "49": {
            "left": 91,
            "top": 602,
            "right": 257,
            "bottom": 1058
        },
        "50": {
            "left": 96,
            "top": 603,
            "right": 262,
            "bottom": 1060
        },
        "51": {
            "left": 100,
            "top": 603,
            "right": 269,
            "bottom": 1061
        },
        "52": {
            "left": 105,
            "top": 604,
            "right": 274,
            "bottom": 1062
        },
        "53": {
            "left": 111,
            "top": 605,
            "right": 280,
            "bottom": 1065
        },
        "54": {
            "left": 116,
            "top": 606,
            "right": 285,
            "bottom": 1066
        },
        "55": {
            "left": 121,
            "top": 605,
            "right": 291,
            "bottom": 1067
        },
        "56": {
            "left": 126,
            "top": 606,
            "right": 296,
            "bottom": 1070
        },
        "57": {
            "left": 131,
            "top": 607,
            "right": 301,
            "bottom": 1071
        },
        "58": {
            "left": 137,
            "top": 608,
            "right": 307,
            "bottom": 1073
        },
        "59": {
            "left": 142,
            "top": 608,
            "right": 313,
            "bottom": 1073
        },
        "60": {
            "left": 147,
            "top": 608,
            "right": 318,
            "bottom": 1076
        },
        "61": {
            "left": 153,
            "top": 607,
            "right": 325,
            "bottom": 1080
        },
        "62": {
            "left": 158,
            "top": 607,
            "right": 333,
            "bottom": 1080
        },
        "63": {
            "left": 164,
            "top": 606,
            "right": 342,
            "bottom": 1080
        },
        "64": {
            "left": 170,
            "top": 605,
            "right": 350,
            "bottom": 1080
        },
        "65": {
            "left": 177,
            "top": 603,
            "right": 357,
            "bottom": 1080
        },
        "66": {
            "left": 184,
            "top": 603,
            "right": 366,
            "bottom": 1080
        },
        "67": {
            "left": 192,
            "top": 603,
            "right": 375,
            "bottom": 1080
        },
        "68": {
            "left": 199,
            "top": 602,
            "right": 384,
            "bottom": 1080
        },
        "69": {
            "left": 207,
            "top": 601,
            "right": 392,
            "bottom": 1080
        },
        "70": {
            "left": 215,
            "top": 600,
            "right": 400,
            "bottom": 1080
        },
        "71": {
            "left": 223,
            "top": 600,
            "right": 410,
            "bottom": 1080
        },
        "72": {
            "left": 231,
            "top": 599,
            "right": 418,
            "bottom": 1080
        },
        "73": {
            "left": 240,
            "top": 599,
            "right": 427,
            "bottom": 1080
        },
        "74": {
            "left": 249,
            "top": 599,
            "right": 436,
            "bottom": 1080
        },
        "75": {
            "left": 259,
            "top": 598,
            "right": 446,
            "bottom": 1080
        },
        "76": {
            "left": 269,
            "top": 598,
            "right": 456,
            "bottom": 1080
        },
        "77": {
            "left": 279,
            "top": 598,
            "right": 464,
            "bottom": 1080
        },
        "78": {
            "left": 288,
            "top": 597,
            "right": 473,
            "bottom": 1080
        },
        "79": {
            "left": 298,
            "top": 597,
            "right": 483,
            "bottom": 1080
        },
        "80": {
            "left": 306,
            "top": 591,
            "right": 494,
            "bottom": 1080
        },
        "81": {
            "left": 314,
            "top": 584,
            "right": 503,
            "bottom": 1080
        },
        "82": {
            "left": 321,
            "top": 578,
            "right": 514,
            "bottom": 1080
        },
        "83": {
            "left": 329,
            "top": 572,
            "right": 524,
            "bottom": 1080
        },
        "84": {
            "left": 338,
            "top": 566,
            "right": 542,
            "bottom": 1079
        },
        "85": {
            "left": 347,
            "top": 561,
            "right": 557,
            "bottom": 1075
        },
        "86": {
            "left": 356,
            "top": 554,
            "right": 575,
            "bottom": 1072
        },
        "87": {
            "left": 365,
            "top": 549,
            "right": 591,
            "bottom": 1069
        },
        "88": {
            "left": 377,
            "top": 548,
            "right": 604,
            "bottom": 1071
        },
        "89": {
            "left": 388,
            "top": 548,
            "right": 616,
            "bottom": 1075
        },
        "90": {
            "left": 400,
            "top": 546,
            "right": 628,
            "bottom": 1077
        },
        "91": {
            "left": 410,
            "top": 545,
            "right": 641,
            "bottom": 1080
        },
        "92": {
            "left": 423,
            "top": 544,
            "right": 651,
            "bottom": 1079
        },
        "93": {
            "left": 434,
            "top": 544,
            "right": 662,
            "bottom": 1080
        },
        "94": {
            "left": 446,
            "top": 543,
            "right": 673,
            "bottom": 1079
        },
        "95": {
            "left": 457,
            "top": 542,
            "right": 683,
            "bottom": 1078
        },
        "96": {
            "left": 472,
            "top": 541,
            "right": 695,
            "bottom": 1079
        },
        "97": {
            "left": 486,
            "top": 539,
            "right": 707,
            "bottom": 1080
        },
        "98": {
            "left": 500,
            "top": 538,
            "right": 719,
            "bottom": 1080
        },
        "99": {
            "left": 515,
            "top": 537,
            "right": 730,
            "bottom": 1080
        },
        "100": {
            "left": 527,
            "top": 535,
            "right": 744,
            "bottom": 1080
        },
        "101": {
            "left": 539,
            "top": 533,
            "right": 758,
            "bottom": 1080
        },
        "102": {
            "left": 551,
            "top": 530,
            "right": 772,
            "bottom": 1080
        },
        "103": {
            "left": 563,
            "top": 529,
            "right": 785,
            "bottom": 1080
        },
        "104": {
            "left": 576,
            "top": 524,
            "right": 802,
            "bottom": 1080
        },
        "105": {
            "left": 590,
            "top": 519,
            "right": 818,
            "bottom": 1080
        },
        "106": {
            "left": 603,
            "top": 515,
            "right": 835,
            "bottom": 1080
        },
        "107": {
            "left": 616,
            "top": 509,
            "right": 852,
            "bottom": 1080
        },
        "108": {
            "left": 628,
            "top": 508,
            "right": 868,
            "bottom": 1080
        },
        "109": {
            "left": 639,
            "top": 508,
            "right": 884,
            "bottom": 1080
        },
        "110": {
            "left": 650,
            "top": 507,
            "right": 900,
            "bottom": 1080
        },
        "111": {
            "left": 660,
            "top": 506,
            "right": 914,
            "bottom": 1080
        },
        "112": {
            "left": 671,
            "top": 506,
            "right": 931,
            "bottom": 1080
        },
        "113": {
            "left": 682,
            "top": 505,
            "right": 947,
            "bottom": 1080
        },
        "114": {
            "left": 700,
            "top": 506,
            "right": 961,
            "bottom": 1080
        },
        "115": {
            "left": 717,
            "top": 506,
            "right": 973,
            "bottom": 1080
        },
        "116": {
            "left": 734,
            "top": 506,
            "right": 987,
            "bottom": 1080
        },
        "117": {
            "left": 751,
            "top": 507,
            "right": 999,
            "bottom": 1080
        },
        "118": {
            "left": 766,
            "top": 507,
            "right": 1016,
            "bottom": 1080
        },
        "119": {
            "left": 779,
            "top": 509,
            "right": 1032,
            "bottom": 1080
        },
        "120": {
            "left": 794,
            "top": 509,
            "right": 1050,
            "bottom": 1080
        },
        "121": {
            "left": 808,
            "top": 511,
            "right": 1065,
            "bottom": 1080
        },
        "122": {
            "left": 822,
            "top": 512,
            "right": 1083,
            "bottom": 1080
        },
        "123": {
            "left": 839,
            "top": 511,
            "right": 1099,
            "bottom": 1080
        },
        "124": {
            "left": 857,
            "top": 510,
            "right": 1114,
            "bottom": 1080
        },
        "125": {
            "left": 875,
            "top": 510,
            "right": 1131,
            "bottom": 1080
        },
        "126": {
            "left": 892,
            "top": 509,
            "right": 1146,
            "bottom": 1080
        },
        "127": {
            "left": 909,
            "top": 508,
            "right": 1162,
            "bottom": 1080
        },
        "128": {
            "left": 925,
            "top": 505,
            "right": 1179,
            "bottom": 1080
        },
        "129": {
            "left": 940,
            "top": 504,
            "right": 1197,
            "bottom": 1080
        },
        "130": {
            "left": 955,
            "top": 501,
            "right": 1215,
            "bottom": 1080
        },
        "131": {
            "left": 970,
            "top": 500,
            "right": 1232,
            "bottom": 1080
        },
        "132": {
            "left": 985,
            "top": 497,
            "right": 1250,
            "bottom": 1080
        },
        "133": {
            "left": 1002,
            "top": 494,
            "right": 1268,
            "bottom": 1080
        },
        "134": {
            "left": 1019,
            "top": 491,
            "right": 1286,
            "bottom": 1080
        },
        "135": {
            "left": 1037,
            "top": 487,
            "right": 1304,
            "bottom": 1080
        },
        "136": {
            "left": 1053,
            "top": 484,
            "right": 1323,
            "bottom": 1080
        },
        "137": {
            "left": 1070,
            "top": 481,
            "right": 1341,
            "bottom": 1080
        },
        "138": {
            "left": 1084,
            "top": 478,
            "right": 1360,
            "bottom": 1080
        },
        "139": {
            "left": 1100,
            "top": 475,
            "right": 1379,
            "bottom": 1080
        },
        "140": {
            "left": 1114,
            "top": 472,
            "right": 1398,
            "bottom": 1080
        },
        "141": {
            "left": 1128,
            "top": 469,
            "right": 1416,
            "bottom": 1080
        },
        "142": {
            "left": 1144,
            "top": 470,
            "right": 1433,
            "bottom": 1080
        },
        "143": {
            "left": 1158,
            "top": 469,
            "right": 1451,
            "bottom": 1080
        },
        "144": {
            "left": 1174,
            "top": 470,
            "right": 1469,
            "bottom": 1080
        },
        "145": {
            "left": 1189,
            "top": 470,
            "right": 1485,
            "bottom": 1080
        },
        "146": {
            "left": 1207,
            "top": 467,
            "right": 1502,
            "bottom": 1080
        },
        "147": {
            "left": 1225,
            "top": 463,
            "right": 1518,
            "bottom": 1080
        },
        "148": {
            "left": 1244,
            "top": 461,
            "right": 1533,
            "bottom": 1080
        },
        "149": {
            "left": 1262,
            "top": 457,
            "right": 1550,
            "bottom": 1080
        }
    }
}