{
    "0_301_2338b": {
        "0": {
            "left": 1076,
            "top": 613,
            "right": 1155,
            "bottom": 808
        },
        "1": {
            "left": 1077,
            "top": 611,
            "right": 1156,
            "bottom": 809
        },
        "2": {
            "left": 1077,
            "top": 610,
            "right": 1156,
            "bottom": 810
        },
        "3": {
            "left": 1078,
            "top": 607,
            "right": 1158,
            "bottom": 811
        },
        "4": {
            "left": 1078,
            "top": 606,
            "right": 1158,
            "bottom": 811
        },
        "5": {
            "left": 1079,
            "top": 604,
            "right": 1159,
            "bottom": 813
        },
        "6": {
            "left": 1080,
            "top": 603,
            "right": 1160,
            "bottom": 813
        },
        "7": {
            "left": 1081,
            "top": 602,
            "right": 1162,
            "bottom": 816
        },
        "8": {
            "left": 1081,
            "top": 601,
            "right": 1162,
            "bottom": 816
        },
        "9": {
            "left": 1082,
            "top": 600,
            "right": 1163,
            "bottom": 817
        },
        "10": {
            "left": 1084,
            "top": 598,
            "right": 1164,
            "bottom": 817
        },
        "11": {
            "left": 1087,
            "top": 597,
            "right": 1166,
            "bottom": 818
        },
        "12": {
            "left": 1089,
            "top": 595,
            "right": 1168,
            "bottom": 817
        },
        "13": {
            "left": 1093,
            "top": 594,
            "right": 1169,
            "bottom": 817
        },
        "14": {
            "left": 1095,
            "top": 592,
            "right": 1170,
            "bottom": 818
        },
        "15": {
            "left": 1097,
            "top": 591,
            "right": 1172,
            "bottom": 819
        },
        "16": {
            "left": 1098,
            "top": 590,
            "right": 1173,
            "bottom": 821
        },
        "17": {
            "left": 1100,
            "top": 589,
            "right": 1174,
            "bottom": 823
        },
        "18": {
            "left": 1101,
            "top": 587,
            "right": 1175,
            "bottom": 823
        },
        "19": {
            "left": 1102,
            "top": 587,
            "right": 1177,
            "bottom": 824
        },
        "20": {
            "left": 1104,
            "top": 588,
            "right": 1180,
            "bottom": 828
        },
        "21": {
            "left": 1104,
            "top": 587,
            "right": 1183,
            "bottom": 830
        },
        "22": {
            "left": 1106,
            "top": 587,
            "right": 1185,
            "bottom": 832
        },
        "23": {
            "left": 1108,
            "top": 585,
            "right": 1187,
            "bottom": 833
        },
        "24": {
            "left": 1111,
            "top": 585,
            "right": 1190,
            "bottom": 835
        },
        "25": {
            "left": 1113,
            "top": 583,
            "right": 1192,
            "bottom": 837
        },
        "26": {
            "left": 1115,
            "top": 583,
            "right": 1194,
            "bottom": 839
        },
        "27": {
            "left": 1117,
            "top": 581,
            "right": 1196,
            "bottom": 841
        },
        "28": {
            "left": 1119,
            "top": 581,
            "right": 1199,
            "bottom": 842
        },
        "29": {
            "left": 1121,
            "top": 581,
            "right": 1201,
            "bottom": 842
        },
        "30": {
            "left": 1124,
            "top": 581,
            "right": 1205,
            "bottom": 843
        },
        "31": {
            "left": 1126,
            "top": 581,
            "right": 1207,
            "bottom": 843
        },
        "32": {
            "left": 1127,
            "top": 580,
            "right": 1211,
            "bottom": 845
        },
        "33": {
            "left": 1129,
            "top": 579,
            "right": 1214,
            "bottom": 845
        },
        "34": {
            "left": 1132,
            "top": 579,
            "right": 1217,
            "bottom": 846
        },
        "35": {
            "left": 1134,
            "top": 577,
            "right": 1221,
            "bottom": 847
        },
        "36": {
            "left": 1136,
            "top": 576,
            "right": 1223,
            "bottom": 847
        },
        "37": {
            "left": 1137,
            "top": 576,
            "right": 1225,
            "bottom": 850
        },
        "38": {
            "left": 1139,
            "top": 575,
            "right": 1227,
            "bottom": 853
        },
        "39": {
            "left": 1139,
            "top": 576,
            "right": 1230,
            "bottom": 855
        },
        "40": {
            "left": 1141,
            "top": 575,
            "right": 1232,
            "bottom": 858
        },
        "41": {
            "left": 1142,
            "top": 574,
            "right": 1234,
            "bottom": 861
        },
        "42": {
            "left": 1144,
            "top": 579,
            "right": 1237,
            "bottom": 867
        },
        "43": {
            "left": 1145,
            "top": 583,
            "right": 1241,
            "bottom": 872
        },
        "44": {
            "left": 1146,
            "top": 588,
            "right": 1243,
            "bottom": 877
        },
        "45": {
            "left": 1148,
            "top": 592,
            "right": 1246,
            "bottom": 883
        },
        "46": {
            "left": 1149,
            "top": 592,
            "right": 1253,
            "bottom": 885
        },
        "47": {
            "left": 1149,
            "top": 594,
            "right": 1258,
            "bottom": 887
        },
        "48": {
            "left": 1150,
            "top": 595,
            "right": 1263,
            "bottom": 890
        },
        "49": {
            "left": 1150,
            "top": 596,
            "right": 1268,
            "bottom": 891
        },
        "50": {
            "left": 1152,
            "top": 591,
            "right": 1270,
            "bottom": 887
        },
        "51": {
            "left": 1153,
            "top": 585,
            "right": 1271,
            "bottom": 884
        },
        "52": {
            "left": 1153,
            "top": 577,
            "right": 1272,
            "bottom": 878
        },
        "53": {
            "left": 1155,
            "top": 572,
            "right": 1273,
            "bottom": 876
        },
        "54": {
            "left": 1157,
            "top": 568,
            "right": 1275,
            "bottom": 873
        },
        "55": {
            "left": 1160,
            "top": 566,
            "right": 1275,
            "bottom": 874
        },
        "56": {
            "left": 1161,
            "top": 563,
            "right": 1275,
            "bottom": 873
        },
        "57": {
            "left": 1162,
            "top": 561,
            "right": 1276,
            "bottom": 873
        },
        "58": {
            "left": 1163,
            "top": 559,
            "right": 1276,
            "bottom": 872
        },
        "59": {
            "left": 1165,
            "top": 558,
            "right": 1275,
            "bottom": 873
        },
        "60": {
            "left": 1168,
            "top": 558,
            "right": 1278,
            "bottom": 876
        },
        "61": {
            "left": 1171,
            "top": 559,
            "right": 1280,
            "bottom": 880
        },
        "62": {
            "left": 1175,
            "top": 560,
            "right": 1282,
            "bottom": 882
        },
        "63": {
            "left": 1178,
            "top": 561,
            "right": 1285,
            "bottom": 884
        },
        "64": {
            "left": 1181,
            "top": 561,
            "right": 1286,
            "bottom": 886
        },
        "65": {
            "left": 1183,
            "top": 560,
            "right": 1287,
            "bottom": 888
        },
        "66": {
            "left": 1185,
            "top": 560,
            "right": 1289,
            "bottom": 890
        },
        "67": {
            "left": 1187,
            "top": 559,
            "right": 1289,
            "bottom": 891
        },
        "68": {
            "left": 1188,
            "top": 558,
            "right": 1290,
            "bottom": 892
        },
        "69": {
            "left": 1189,
            "top": 558,
            "right": 1293,
            "bottom": 893
        },
        "70": {
            "left": 1189,
            "top": 556,
            "right": 1296,
            "bottom": 894
        },
        "71": {
            "left": 1191,
            "top": 555,
            "right": 1301,
            "bottom": 894
        },
        "72": {
            "left": 1191,
            "top": 555,
            "right": 1304,
            "bottom": 895
        },
        "73": {
            "left": 1193,
            "top": 554,
            "right": 1308,
            "bottom": 895
        },
        "74": {
            "left": 1193,
            "top": 552,
            "right": 1312,
            "bottom": 896
        },
        "75": {
            "left": 1195,
            "top": 548,
            "right": 1313,
            "bottom": 893
        },
        "76": {
            "left": 1198,
            "top": 544,
            "right": 1316,
            "bottom": 891
        },
        "77": {
            "left": 1201,
            "top": 539,
            "right": 1316,
            "bottom": 890
        },
        "78": {
            "left": 1204,
            "top": 535,
            "right": 1319,
            "bottom": 887
        },
        "79": {
            "left": 1205,
            "top": 530,
            "right": 1319,
            "bottom": 884
        },
        "80": {
            "left": 1207,
            "top": 527,
            "right": 1321,
            "bottom": 883
        },
        "81": {
            "left": 1209,
            "top": 526,
            "right": 1323,
            "bottom": 882
        },
        "82": {
            "left": 1211,
            "top": 526,
            "right": 1326,
            "bottom": 883
        },
        "83": {
            "left": 1209,
            "top": 528,
            "right": 1329,
            "bottom": 886
        },
        "84": {
            "left": 1204,
            "top": 534,
            "right": 1336,
            "bottom": 895
        },
        "85": {
            "left": 1196,
            "top": 543,
            "right": 1342,
            "bottom": 907
        },
        "86": {
            "left": 1190,
            "top": 548,
            "right": 1349,
            "bottom": 914
        },
        "87": {
            "left": 1184,
            "top": 553,
            "right": 1355,
            "bottom": 920
        },
        "88": {
            "left": 1175,
            "top": 558,
            "right": 1360,
            "bottom": 927
        },
        "89": {
            "left": 1169,
            "top": 561,
            "right": 1364,
            "bottom": 932
        },
        "90": {
            "left": 1167,
            "top": 562,
            "right": 1367,
            "bottom": 933
        },
        "91": {
            "left": 1167,
            "top": 559,
            "right": 1362,
            "bottom": 930
        },
        "92": {
            "left": 1167,
            "top": 556,
            "right": 1359,
            "bottom": 927
        },
        "93": {
            "left": 1167,
            "top": 554,
            "right": 1355,
            "bottom": 927
        },
        "94": {
            "left": 1166,
            "top": 552,
            "right": 1351,
            "bottom": 925
        },
        "95": {
            "left": 1166,
            "top": 550,
            "right": 1349,
            "bottom": 924
        },
        "96": {
            "left": 1165,
            "top": 549,
            "right": 1347,
            "bottom": 923
        },
        "97": {
            "left": 1164,
            "top": 548,
            "right": 1344,
            "bottom": 923
        },
        "98": {
            "left": 1162,
            "top": 547,
            "right": 1342,
            "bottom": 925
        },
        "99": {
            "left": 1160,
            "top": 548,
            "right": 1326,
            "bottom": 926
        },
        "100": {
            "left": 1155,
            "top": 549,
            "right": 1314,
            "bottom": 929
        },
        "101": {
            "left": 1150,
            "top": 548,
            "right": 1306,
            "bottom": 931
        },
        "102": {
            "left": 1141,
            "top": 549,
            "right": 1304,
            "bottom": 937
        },
        "103": {
            "left": 1132,
            "top": 549,
            "right": 1308,
            "bottom": 944
        },
        "104": {
            "left": 1123,
            "top": 550,
            "right": 1312,
            "bottom": 950
        },
        "105": {
            "left": 1110,
            "top": 552,
            "right": 1314,
            "bottom": 955
        },
        "106": {
            "left": 1097,
            "top": 554,
            "right": 1319,
            "bottom": 959
        },
        "107": {
            "left": 1083,
            "top": 557,
            "right": 1320,
            "bottom": 963
        },
        "108": {
            "left": 1072,
            "top": 559,
            "right": 1322,
            "bottom": 967
        },
        "109": {
            "left": 1065,
            "top": 560,
            "right": 1321,
            "bottom": 969
        },
        "110": {
            "left": 1062,
            "top": 559,
            "right": 1312,
            "bottom": 972
        },
        "111": {
            "left": 1061,
            "top": 559,
            "right": 1300,
            "bottom": 973
        },
        "112": {
            "left": 1062,
            "top": 557,
            "right": 1281,
            "bottom": 974
        },
        "113": {
            "left": 1066,
            "top": 556,
            "right": 1259,
            "bottom": 975
        },
        "114": {
            "left": 1070,
            "top": 554,
            "right": 1240,
            "bottom": 977
        },
        "115": {
            "left": 1059,
            "top": 552,
            "right": 1228,
            "bottom": 981
        },
        "116": {
            "left": 1048,
            "top": 549,
            "right": 1213,
            "bottom": 983
        },
        "117": {
            "left": 1037,
            "top": 548,
            "right": 1200,
            "bottom": 984
        },
        "118": {
            "left": 1026,
            "top": 545,
            "right": 1185,
            "bottom": 987
        },
        "119": {
            "left": 1000,
            "top": 546,
            "right": 1193,
            "bottom": 988
        },
        "120": {
            "left": 975,
            "top": 547,
            "right": 1202,
            "bottom": 990
        },
        "121": {
            "left": 949,
            "top": 547,
            "right": 1210,
            "bottom": 990
        },
        "122": {
            "left": 923,
            "top": 548,
            "right": 1218,
            "bottom": 991
        },
        "123": {
            "left": 922,
            "top": 548,
            "right": 1206,
            "bottom": 991
        },
        "124": {
            "left": 922,
            "top": 547,
            "right": 1196,
            "bottom": 992
        },
        "125": {
            "left": 920,
            "top": 547,
            "right": 1185,
            "bottom": 992
        },
        "126": {
            "left": 924,
            "top": 544,
            "right": 1160,
            "bottom": 995
        },
        "127": {
            "left": 928,
            "top": 541,
            "right": 1133,
            "bottom": 998
        },
        "128": {
            "left": 932,
            "top": 538,
            "right": 1108,
            "bottom": 1000
        },
        "129": {
            "left": 922,
            "top": 535,
            "right": 1094,
            "bottom": 1004
        },
        "130": {
            "left": 911,
            "top": 532,
            "right": 1081,
            "bottom": 1007
        },
        "131": {
            "left": 901,
            "top": 529,
            "right": 1067,
            "bottom": 1011
        },
        "132": {
            "left": 878,
            "top": 531,
            "right": 1070,
            "bottom": 1012
        },
        "133": {
            "left": 854,
            "top": 533,
            "right": 1073,
            "bottom": 1012
        },
        "134": {
            "left": 832,
            "top": 536,
            "right": 1076,
            "bottom": 1011
        },
        "135": {
            "left": 808,
            "top": 538,
            "right": 1078,
            "bottom": 1012
        },
        "136": {
            "left": 806,
            "top": 537,
            "right": 1068,
            "bottom": 1014
        },
        "137": {
            "left": 803,
            "top": 536,
            "right": 1060,
            "bottom": 1017
        },
        "138": {
            "left": 800,
            "top": 535,
            "right": 1050,
            "bottom": 1017
        },
        "139": {
            "left": 797,
            "top": 533,
            "right": 1041,
            "bottom": 1019
        },
        "140": {
            "left": 797,
            "top": 530,
            "right": 1016,
            "bottom": 1022
        },
        "141": {
            "left": 798,
            "top": 526,
            "right": 993,
            "bottom": 1025
        },
        "142": {
            "left": 797,
            "top": 523,
            "right": 967,
            "bottom": 1027
        },
        "143": {
            "left": 798,
            "top": 519,
            "right": 942,
            "bottom": 1029
        },
        "144": {
            "left": 775,
            "top": 518,
            "right": 940,
            "bottom": 1032
        },
        "145": {
            "left": 752,
            "top": 516,
            "right": 937,
            "bottom": 1034
        },
        "146": {
            "left": 730,
            "top": 516,
            "right": 935,
            "bottom": 1037
        },
        "147": {
            "left": 702,
            "top": 518,
            "right": 942,
            "bottom": 1036
        },
        "148": {
            "left": 672,
            "top": 520,
            "right": 948,
            "bottom": 1034
        },
        "149": {
            "left": 644,
            "top": 523,
            "right": 956,
            "bottom": 1033
        },
        "150": {
            "left": 632,
            "top": 523,
            "right": 955,
            "bottom": 1037
        },
        "151": {
            "left": 620,
            "top": 524,
            "right": 955,
            "bottom": 1040
        },
        "152": {
            "left": 622,
            "top": 522,
            "right": 937,
            "bottom": 1040
        },
        "153": {
            "left": 625,
            "top": 521,
            "right": 920,
            "bottom": 1039
        },
        "154": {
            "left": 628,
            "top": 520,
            "right": 902,
            "bottom": 1040
        },
        "155": {
            "left": 628,
            "top": 516,
            "right": 873,
            "bottom": 1043
        },
        "156": {
            "left": 628,
            "top": 511,
            "right": 843,
            "bottom": 1047
        },
        "157": {
            "left": 628,
            "top": 507,
            "right": 815,
            "bottom": 1051
        },
        "158": {
            "left": 609,
            "top": 508,
            "right": 807,
            "bottom": 1052
        },
        "159": {
            "left": 591,
            "top": 509,
            "right": 801,
            "bottom": 1053
        },
        "160": {
            "left": 572,
            "top": 510,
            "right": 793,
            "bottom": 1053
        },
        "161": {
            "left": 553,
            "top": 511,
            "right": 785,
            "bottom": 1054
        },
        "162": {
            "left": 530,
            "top": 511,
            "right": 790,
            "bottom": 1055
        },
        "163": {
            "left": 508,
            "top": 511,
            "right": 792,
            "bottom": 1059
        },
        "164": {
            "left": 485,
            "top": 511,
            "right": 797,
            "bottom": 1060
        },
        "165": {
            "left": 481,
            "top": 510,
            "right": 789,
            "bottom": 1063
        },
        "166": {
            "left": 475,
            "top": 509,
            "right": 780,
            "bottom": 1068
        },
        "167": {
            "left": 471,
            "top": 509,
            "right": 772,
            "bottom": 1070
        },
        "168": {
            "left": 474,
            "top": 506,
            "right": 745,
            "bottom": 1071
        },
        "169": {
            "left": 479,
            "top": 502,
            "right": 719,
            "bottom": 1071
        },
        "170": {
            "left": 482,
            "top": 500,
            "right": 692,
            "bottom": 1072
        },
        "171": {
            "left": 469,
            "top": 498,
            "right": 674,
            "bottom": 1073
        },
        "172": {
            "left": 456,
            "top": 495,
            "right": 658,
            "bottom": 1076
        },
        "173": {
            "left": 443,
            "top": 494,
            "right": 640,
            "bottom": 1077
        },
        "174": {
            "left": 430,
            "top": 491,
            "right": 622,
            "bottom": 1078
        },
        "175": {
            "left": 400,
            "top": 493,
            "right": 628,
            "bottom": 1079
        },
        "176": {
            "left": 370,
            "top": 497,
            "right": 636,
            "bottom": 1080
        },
        "177": {
            "left": 340,
            "top": 499,
            "right": 641,
            "bottom": 1080
        },
        "178": {
            "left": 309,
            "top": 502,
            "right": 648,
            "bottom": 1080
        },
        "179": {
            "left": 303,
            "top": 501,
            "right": 643,
            "bottom": 1080
        },
        "180": {
            "left": 295,
            "top": 500,
            "right": 639,
            "bottom": 1080
        },
        "181": {
            "left": 289,
            "top": 500,
            "right": 634,
            "bottom": 1080
        },
        "182": {
            "left": 294,
            "top": 499,
            "right": 611,
            "bottom": 1080
        },
        "183": {
            "left": 298,
            "top": 497,
            "right": 585,
            "bottom": 1080
        },
        "184": {
            "left": 304,
            "top": 496,
            "right": 561,
            "bottom": 1080
        },
        "185": {
            "left": 297,
            "top": 493,
            "right": 528,
            "bottom": 1080
        },
        "186": {
            "left": 291,
            "top": 491,
            "right": 493,
            "bottom": 1080
        },
        "187": {
            "left": 285,
            "top": 488,
            "right": 460,
            "bottom": 1080
        },
        "188": {
            "left": 265,
            "top": 487,
            "right": 458,
            "bottom": 1080
        },
        "189": {
            "left": 244,
            "top": 486,
            "right": 454,
            "bottom": 1080
        },
        "190": {
            "left": 224,
            "top": 485,
            "right": 452,
            "bottom": 1080
        },
        "191": {
            "left": 189,
            "top": 485,
            "right": 459,
            "bottom": 1080
        },
        "192": {
            "left": 157,
            "top": 486,
            "right": 465,
            "bottom": 1080
        },
        "193": {
            "left": 122,
            "top": 485,
            "right": 471,
            "bottom": 1080
        },
        "194": {
            "left": 117,
            "top": 486,
            "right": 461,
            "bottom": 1080
        },
        "195": {
            "left": 113,
            "top": 486,
            "right": 452,
            "bottom": 1080
        },
        "196": {
            "left": 108,
            "top": 487,
            "right": 442,
            "bottom": 1080
        },
        "197": {
            "left": 111,
            "top": 481,
            "right": 411,
            "bottom": 1080
        },
        "198": {
            "left": 114,
            "top": 477,
            "right": 381,
            "bottom": 1080
        },
        "199": {
            "left": 117,
            "top": 472,
            "right": 351,
            "bottom": 1080
        },
        "200": {
            "left": 104,
            "top": 470,
            "right": 318,
            "bottom": 1080
        },
        "201": {
            "left": 93,
            "top": 468,
            "right": 288,
            "bottom": 1080
        },
        "202": {
            "left": 80,
            "top": 466,
            "right": 255,
            "bottom": 1080
        },
        "203": {
            "left": 49,
            "top": 465,
            "right": 260,
            "bottom": 1080
        },
        "204": {
            "left": 17,
            "top": 466,
            "right": 267,
            "bottom": 1080
        },
        "205": {
            "left": 0,
            "top": 466,
            "right": 267,
            "bottom": 1080
        },
        "206": {
            "left": 0,
            "top": 466,
            "right": 263,
            "bottom": 1080
        },
        "207": {
            "left": 0,
            "top": 464,
            "right": 256,
            "bottom": 1080
        },
        "208": {
            "left": 0,
            "top": 462,
            "right": 250,
            "bottom": 1080
        },
        "209": {
            "left": 0,
            "top": 461,
            "right": 243,
            "bottom": 1080
        }
    },
    "0_301_2333b": {
        "5": {
            "left": 1174,
            "top": 625,
            "right": 1226,
            "bottom": 796
        },
        "6": {
            "left": 1176,
            "top": 623,
            "right": 1228,
            "bottom": 799
        },
        "7": {
            "left": 1177,
            "top": 621,
            "right": 1227,
            "bottom": 801
        },
        "8": {
            "left": 1176,
            "top": 618,
            "right": 1229,
            "bottom": 803
        },
        "9": {
            "left": 1174,
            "top": 616,
            "right": 1231,
            "bottom": 804
        },
        "10": {
            "left": 1176,
            "top": 613,
            "right": 1234,
            "bottom": 805
        },
        "11": {
            "left": 1178,
            "top": 611,
            "right": 1236,
            "bottom": 804
        },
        "12": {
            "left": 1180,
            "top": 608,
            "right": 1239,
            "bottom": 805
        },
        "13": {
            "left": 1181,
            "top": 606,
            "right": 1243,
            "bottom": 803
        },
        "14": {
            "left": 1183,
            "top": 604,
            "right": 1246,
            "bottom": 802
        },
        "15": {
            "left": 1185,
            "top": 602,
            "right": 1250,
            "bottom": 800
        },
        "16": {
            "left": 1185,
            "top": 601,
            "right": 1255,
            "bottom": 803
        },
        "17": {
            "left": 1186,
            "top": 601,
            "right": 1260,
            "bottom": 806
        },
        "18": {
            "left": 1186,
            "top": 600,
            "right": 1265,
            "bottom": 806
        },
        "19": {
            "left": 1187,
            "top": 599,
            "right": 1268,
            "bottom": 809
        },
        "20": {
            "left": 1187,
            "top": 597,
            "right": 1271,
            "bottom": 811
        },
        "21": {
            "left": 1188,
            "top": 594,
            "right": 1273,
            "bottom": 813
        },
        "22": {
            "left": 1189,
            "top": 593,
            "right": 1276,
            "bottom": 815
        },
        "23": {
            "left": 1191,
            "top": 594,
            "right": 1278,
            "bottom": 817
        },
        "24": {
            "left": 1193,
            "top": 595,
            "right": 1281,
            "bottom": 821
        },
        "25": {
            "left": 1195,
            "top": 596,
            "right": 1283,
            "bottom": 822
        },
        "26": {
            "left": 1197,
            "top": 597,
            "right": 1285,
            "bottom": 824
        },
        "27": {
            "left": 1199,
            "top": 597,
            "right": 1287,
            "bottom": 825
        },
        "28": {
            "left": 1202,
            "top": 597,
            "right": 1290,
            "bottom": 825
        },
        "29": {
            "left": 1204,
            "top": 595,
            "right": 1292,
            "bottom": 826
        },
        "30": {
            "left": 1206,
            "top": 595,
            "right": 1294,
            "bottom": 826
        },
        "31": {
            "left": 1208,
            "top": 593,
            "right": 1296,
            "bottom": 827
        },
        "32": {
            "left": 1211,
            "top": 591,
            "right": 1299,
            "bottom": 830
        },
        "33": {
            "left": 1213,
            "top": 588,
            "right": 1301,
            "bottom": 831
        },
        "34": {
            "left": 1215,
            "top": 586,
            "right": 1303,
            "bottom": 831
        },
        "35": {
            "left": 1218,
            "top": 587,
            "right": 1305,
            "bottom": 831
        },
        "36": {
            "left": 1220,
            "top": 587,
            "right": 1304,
            "bottom": 831
        },
        "37": {
            "left": 1224,
            "top": 588,
            "right": 1305,
            "bottom": 831
        },
        "38": {
            "left": 1226,
            "top": 588,
            "right": 1307,
            "bottom": 832
        },
        "39": {
            "left": 1227,
            "top": 588,
            "right": 1308,
            "bottom": 836
        },
        "40": {
            "left": 1229,
            "top": 588,
            "right": 1310,
            "bottom": 837
        },
        "41": {
            "left": 1229,
            "top": 591,
            "right": 1313,
            "bottom": 841
        },
        "42": {
            "left": 1230,
            "top": 593,
            "right": 1317,
            "bottom": 846
        },
        "43": {
            "left": 1230,
            "top": 596,
            "right": 1318,
            "bottom": 849
        },
        "44": {
            "left": 1230,
            "top": 599,
            "right": 1321,
            "bottom": 853
        },
        "45": {
            "left": 1232,
            "top": 603,
            "right": 1323,
            "bottom": 859
        },
        "46": {
            "left": 1233,
            "top": 607,
            "right": 1324,
            "bottom": 863
        },
        "47": {
            "left": 1235,
            "top": 610,
            "right": 1326,
            "bottom": 867
        },
        "48": {
            "left": 1236,
            "top": 614,
            "right": 1327,
            "bottom": 871
        },
        "49": {
            "left": 1237,
            "top": 609,
            "right": 1330,
            "bottom": 869
        },
        "50": {
            "left": 1237,
            "top": 604,
            "right": 1334,
            "bottom": 865
        },
        "51": {
            "left": 1237,
            "top": 600,
            "right": 1338,
            "bottom": 861
        },
        "52": {
            "left": 1238,
            "top": 595,
            "right": 1342,
            "bottom": 857
        },
        "53": {
            "left": 1239,
            "top": 590,
            "right": 1343,
            "bottom": 856
        },
        "54": {
            "left": 1241,
            "top": 584,
            "right": 1345,
            "bottom": 854
        },
        "55": {
            "left": 1242,
            "top": 580,
            "right": 1344,
            "bottom": 851
        },
        "56": {
            "left": 1243,
            "top": 575,
            "right": 1345,
            "bottom": 849
        },
        "57": {
            "left": 1244,
            "top": 576,
            "right": 1348,
            "bottom": 850
        },
        "58": {
            "left": 1245,
            "top": 576,
            "right": 1349,
            "bottom": 852
        },
        "59": {
            "left": 1247,
            "top": 576,
            "right": 1352,
            "bottom": 852
        },
        "60": {
            "left": 1248,
            "top": 577,
            "right": 1353,
            "bottom": 855
        },
        "61": {
            "left": 1248,
            "top": 578,
            "right": 1355,
            "bottom": 856
        },
        "62": {
            "left": 1249,
            "top": 579,
            "right": 1358,
            "bottom": 858
        },
        "63": {
            "left": 1250,
            "top": 579,
            "right": 1359,
            "bottom": 862
        },
        "64": {
            "left": 1251,
            "top": 579,
            "right": 1361,
            "bottom": 863
        },
        "65": {
            "left": 1252,
            "top": 579,
            "right": 1362,
            "bottom": 866
        },
        "66": {
            "left": 1251,
            "top": 579,
            "right": 1365,
            "bottom": 867
        },
        "67": {
            "left": 1250,
            "top": 578,
            "right": 1368,
            "bottom": 867
        },
        "68": {
            "left": 1250,
            "top": 578,
            "right": 1370,
            "bottom": 867
        },
        "69": {
            "left": 1249,
            "top": 577,
            "right": 1373,
            "bottom": 868
        },
        "70": {
            "left": 1250,
            "top": 576,
            "right": 1376,
            "bottom": 869
        },
        "71": {
            "left": 1251,
            "top": 576,
            "right": 1378,
            "bottom": 869
        },
        "72": {
            "left": 1252,
            "top": 576,
            "right": 1379,
            "bottom": 871
        },
        "73": {
            "left": 1252,
            "top": 576,
            "right": 1382,
            "bottom": 871
        },
        "74": {
            "left": 1255,
            "top": 573,
            "right": 1379,
            "bottom": 869
        },
        "75": {
            "left": 1257,
            "top": 568,
            "right": 1376,
            "bottom": 868
        },
        "76": {
            "left": 1260,
            "top": 565,
            "right": 1374,
            "bottom": 866
        },
        "77": {
            "left": 1262,
            "top": 560,
            "right": 1371,
            "bottom": 864
        },
        "78": {
            "left": 1264,
            "top": 557,
            "right": 1371,
            "bottom": 862
        },
        "79": {
            "left": 1267,
            "top": 554,
            "right": 1372,
            "bottom": 859
        },
        "80": {
            "left": 1268,
            "top": 550,
            "right": 1372,
            "bottom": 856
        },
        "81": {
            "left": 1270,
            "top": 547,
            "right": 1372,
            "bottom": 853
        },
        "82": {
            "left": 1271,
            "top": 552,
            "right": 1376,
            "bottom": 860
        },
        "83": {
            "left": 1271,
            "top": 556,
            "right": 1378,
            "bottom": 864
        },
        "84": {
            "left": 1272,
            "top": 560,
            "right": 1382,
            "bottom": 870
        },
        "85": {
            "left": 1272,
            "top": 564,
            "right": 1385,
            "bottom": 874
        },
        "86": {
            "left": 1273,
            "top": 568,
            "right": 1387,
            "bottom": 880
        },
        "87": {
            "left": 1274,
            "top": 572,
            "right": 1389,
            "bottom": 884
        },
        "88": {
            "left": 1274,
            "top": 577,
            "right": 1389,
            "bottom": 890
        },
        "89": {
            "left": 1274,
            "top": 581,
            "right": 1392,
            "bottom": 894
        },
        "90": {
            "left": 1275,
            "top": 584,
            "right": 1394,
            "bottom": 899
        },
        "91": {
            "left": 1276,
            "top": 581,
            "right": 1395,
            "bottom": 896
        },
        "92": {
            "left": 1277,
            "top": 578,
            "right": 1396,
            "bottom": 895
        },
        "93": {
            "left": 1278,
            "top": 574,
            "right": 1396,
            "bottom": 891
        },
        "94": {
            "left": 1279,
            "top": 571,
            "right": 1397,
            "bottom": 889
        },
        "95": {
            "left": 1280,
            "top": 568,
            "right": 1398,
            "bottom": 886
        },
        "96": {
            "left": 1283,
            "top": 566,
            "right": 1397,
            "bottom": 888
        },
        "97": {
            "left": 1285,
            "top": 565,
            "right": 1395,
            "bottom": 890
        },
        "98": {
            "left": 1287,
            "top": 562,
            "right": 1396,
            "bottom": 892
        },
        "99": {
            "left": 1289,
            "top": 560,
            "right": 1394,
            "bottom": 894
        },
        "100": {
            "left": 1291,
            "top": 558,
            "right": 1393,
            "bottom": 896
        },
        "101": {
            "left": 1291,
            "top": 561,
            "right": 1393,
            "bottom": 896
        },
        "102": {
            "left": 1291,
            "top": 563,
            "right": 1393,
            "bottom": 898
        },
        "103": {
            "left": 1291,
            "top": 564,
            "right": 1393,
            "bottom": 898
        },
        "104": {
            "left": 1291,
            "top": 566,
            "right": 1393,
            "bottom": 898
        },
        "105": {
            "left": 1289,
            "top": 565,
            "right": 1396,
            "bottom": 903
        },
        "106": {
            "left": 1287,
            "top": 564,
            "right": 1400,
            "bottom": 904
        },
        "107": {
            "left": 1286,
            "top": 563,
            "right": 1401,
            "bottom": 908
        },
        "108": {
            "left": 1284,
            "top": 561,
            "right": 1404,
            "bottom": 910
        },
        "109": {
            "left": 1281,
            "top": 562,
            "right": 1405,
            "bottom": 911
        },
        "110": {
            "left": 1279,
            "top": 563,
            "right": 1405,
            "bottom": 910
        },
        "111": {
            "left": 1276,
            "top": 564,
            "right": 1406,
            "bottom": 911
        },
        "112": {
            "left": 1274,
            "top": 564,
            "right": 1405,
            "bottom": 909
        },
        "113": {
            "left": 1274,
            "top": 565,
            "right": 1405,
            "bottom": 912
        },
        "114": {
            "left": 1273,
            "top": 565,
            "right": 1403,
            "bottom": 914
        },
        "115": {
            "left": 1273,
            "top": 565,
            "right": 1403,
            "bottom": 914
        },
        "116": {
            "left": 1273,
            "top": 566,
            "right": 1400,
            "bottom": 917
        },
        "117": {
            "left": 1272,
            "top": 565,
            "right": 1399,
            "bottom": 917
        },
        "118": {
            "left": 1270,
            "top": 564,
            "right": 1396,
            "bottom": 920
        },
        "119": {
            "left": 1269,
            "top": 563,
            "right": 1395,
            "bottom": 920
        },
        "120": {
            "left": 1267,
            "top": 562,
            "right": 1391,
            "bottom": 923
        },
        "121": {
            "left": 1266,
            "top": 561,
            "right": 1390,
            "bottom": 923
        },
        "122": {
            "left": 1263,
            "top": 562,
            "right": 1390,
            "bottom": 924
        },
        "123": {
            "left": 1260,
            "top": 563,
            "right": 1391,
            "bottom": 925
        },
        "124": {
            "left": 1256,
            "top": 563,
            "right": 1391,
            "bottom": 924
        },
        "125": {
            "left": 1253,
            "top": 564,
            "right": 1390,
            "bottom": 925
        },
        "126": {
            "left": 1243,
            "top": 564,
            "right": 1389,
            "bottom": 928
        },
        "127": {
            "left": 1234,
            "top": 562,
            "right": 1390,
            "bottom": 929
        },
        "128": {
            "left": 1223,
            "top": 561,
            "right": 1388,
            "bottom": 932
        },
        "129": {
            "left": 1214,
            "top": 560,
            "right": 1386,
            "bottom": 934
        },
        "130": {
            "left": 1214,
            "top": 561,
            "right": 1385,
            "bottom": 936
        },
        "131": {
            "left": 1215,
            "top": 561,
            "right": 1385,
            "bottom": 939
        },
        "132": {
            "left": 1216,
            "top": 562,
            "right": 1382,
            "bottom": 940
        },
        "133": {
            "left": 1216,
            "top": 563,
            "right": 1381,
            "bottom": 942
        },
        "134": {
            "left": 1215,
            "top": 562,
            "right": 1369,
            "bottom": 945
        },
        "135": {
            "left": 1212,
            "top": 561,
            "right": 1358,
            "bottom": 945
        },
        "136": {
            "left": 1211,
            "top": 560,
            "right": 1347,
            "bottom": 948
        },
        "137": {
            "left": 1209,
            "top": 559,
            "right": 1335,
            "bottom": 949
        },
        "138": {
            "left": 1206,
            "top": 559,
            "right": 1330,
            "bottom": 949
        },
        "139": {
            "left": 1203,
            "top": 559,
            "right": 1327,
            "bottom": 949
        },
        "140": {
            "left": 1201,
            "top": 559,
            "right": 1323,
            "bottom": 949
        },
        "141": {
            "left": 1184,
            "top": 561,
            "right": 1328,
            "bottom": 952
        },
        "142": {
            "left": 1167,
            "top": 564,
            "right": 1332,
            "bottom": 955
        },
        "143": {
            "left": 1150,
            "top": 566,
            "right": 1337,
            "bottom": 958
        },
        "144": {
            "left": 1134,
            "top": 568,
            "right": 1340,
            "bottom": 960
        },
        "145": {
            "left": 1130,
            "top": 569,
            "right": 1341,
            "bottom": 965
        },
        "146": {
            "left": 1125,
            "top": 569,
            "right": 1342,
            "bottom": 969
        },
        "147": {
            "left": 1121,
            "top": 571,
            "right": 1343,
            "bottom": 974
        },
        "148": {
            "left": 1122,
            "top": 571,
            "right": 1332,
            "bottom": 976
        },
        "149": {
            "left": 1124,
            "top": 572,
            "right": 1324,
            "bottom": 977
        },
        "150": {
            "left": 1125,
            "top": 573,
            "right": 1313,
            "bottom": 979
        },
        "151": {
            "left": 1125,
            "top": 571,
            "right": 1294,
            "bottom": 980
        },
        "152": {
            "left": 1125,
            "top": 567,
            "right": 1273,
            "bottom": 980
        },
        "153": {
            "left": 1126,
            "top": 564,
            "right": 1253,
            "bottom": 981
        },
        "154": {
            "left": 1110,
            "top": 564,
            "right": 1251,
            "bottom": 983
        },
        "155": {
            "left": 1096,
            "top": 563,
            "right": 1250,
            "bottom": 985
        },
        "156": {
            "left": 1080,
            "top": 563,
            "right": 1249,
            "bottom": 988
        },
        "157": {
            "left": 1065,
            "top": 564,
            "right": 1250,
            "bottom": 986
        },
        "158": {
            "left": 1051,
            "top": 567,
            "right": 1251,
            "bottom": 985
        },
        "159": {
            "left": 1036,
            "top": 569,
            "right": 1253,
            "bottom": 983
        },
        "160": {
            "left": 1037,
            "top": 571,
            "right": 1248,
            "bottom": 985
        },
        "161": {
            "left": 1037,
            "top": 572,
            "right": 1242,
            "bottom": 985
        },
        "162": {
            "left": 1038,
            "top": 574,
            "right": 1238,
            "bottom": 987
        },
        "163": {
            "left": 1042,
            "top": 570,
            "right": 1217,
            "bottom": 987
        },
        "164": {
            "left": 1046,
            "top": 567,
            "right": 1194,
            "bottom": 989
        },
        "165": {
            "left": 1051,
            "top": 564,
            "right": 1173,
            "bottom": 989
        },
        "166": {
            "left": 1036,
            "top": 563,
            "right": 1168,
            "bottom": 992
        },
        "167": {
            "left": 1022,
            "top": 562,
            "right": 1165,
            "bottom": 993
        },
        "168": {
            "left": 1007,
            "top": 561,
            "right": 1159,
            "bottom": 996
        },
        "169": {
            "left": 993,
            "top": 559,
            "right": 1154,
            "bottom": 998
        },
        "170": {
            "left": 981,
            "top": 561,
            "right": 1156,
            "bottom": 997
        },
        "171": {
            "left": 970,
            "top": 563,
            "right": 1159,
            "bottom": 998
        },
        "172": {
            "left": 957,
            "top": 564,
            "right": 1161,
            "bottom": 998
        },
        "173": {
            "left": 946,
            "top": 566,
            "right": 1163,
            "bottom": 997
        },
        "174": {
            "left": 948,
            "top": 564,
            "right": 1154,
            "bottom": 1000
        },
        "175": {
            "left": 950,
            "top": 562,
            "right": 1147,
            "bottom": 1002
        },
        "176": {
            "left": 952,
            "top": 560,
            "right": 1139,
            "bottom": 1005
        },
        "177": {
            "left": 954,
            "top": 559,
            "right": 1130,
            "bottom": 1007
        },
        "178": {
            "left": 949,
            "top": 556,
            "right": 1118,
            "bottom": 1009
        },
        "179": {
            "left": 945,
            "top": 552,
            "right": 1106,
            "bottom": 1012
        },
        "180": {
            "left": 939,
            "top": 549,
            "right": 1092,
            "bottom": 1014
        },
        "181": {
            "left": 935,
            "top": 545,
            "right": 1079,
            "bottom": 1015
        },
        "182": {
            "left": 913,
            "top": 547,
            "right": 1076,
            "bottom": 1015
        },
        "183": {
            "left": 893,
            "top": 551,
            "right": 1076,
            "bottom": 1016
        },
        "184": {
            "left": 871,
            "top": 553,
            "right": 1073,
            "bottom": 1015
        },
        "185": {
            "left": 861,
            "top": 556,
            "right": 1076,
            "bottom": 1016
        },
        "186": {
            "left": 850,
            "top": 558,
            "right": 1078,
            "bottom": 1018
        },
        "187": {
            "left": 839,
            "top": 560,
            "right": 1082,
            "bottom": 1018
        },
        "188": {
            "left": 841,
            "top": 560,
            "right": 1075,
            "bottom": 1017
        },
        "189": {
            "left": 844,
            "top": 559,
            "right": 1067,
            "bottom": 1016
        },
        "190": {
            "left": 845,
            "top": 559,
            "right": 1060,
            "bottom": 1015
        },
        "191": {
            "left": 847,
            "top": 557,
            "right": 1040,
            "bottom": 1017
        },
        "192": {
            "left": 848,
            "top": 555,
            "right": 1019,
            "bottom": 1019
        },
        "193": {
            "left": 850,
            "top": 552,
            "right": 999,
            "bottom": 1021
        },
        "194": {
            "left": 841,
            "top": 552,
            "right": 987,
            "bottom": 1022
        },
        "195": {
            "left": 834,
            "top": 550,
            "right": 978,
            "bottom": 1024
        },
        "196": {
            "left": 825,
            "top": 550,
            "right": 966,
            "bottom": 1025
        },
        "197": {
            "left": 805,
            "top": 551,
            "right": 970,
            "bottom": 1026
        },
        "198": {
            "left": 785,
            "top": 553,
            "right": 973,
            "bottom": 1027
        },
        "199": {
            "left": 765,
            "top": 554,
            "right": 975,
            "bottom": 1028
        },
        "200": {
            "left": 745,
            "top": 555,
            "right": 979,
            "bottom": 1028
        },
        "201": {
            "left": 741,
            "top": 555,
            "right": 977,
            "bottom": 1030
        },
        "202": {
            "left": 738,
            "top": 554,
            "right": 975,
            "bottom": 1033
        },
        "203": {
            "left": 735,
            "top": 554,
            "right": 974,
            "bottom": 1036
        },
        "204": {
            "left": 735,
            "top": 552,
            "right": 961,
            "bottom": 1036
        },
        "205": {
            "left": 736,
            "top": 552,
            "right": 946,
            "bottom": 1039
        },
        "206": {
            "left": 736,
            "top": 550,
            "right": 933,
            "bottom": 1040
        },
        "207": {
            "left": 733,
            "top": 548,
            "right": 913,
            "bottom": 1042
        },
        "208": {
            "left": 732,
            "top": 543,
            "right": 893,
            "bottom": 1044
        },
        "209": {
            "left": 729,
            "top": 540,
            "right": 873,
            "bottom": 1047
        }
    }
}