{
    "0_176_1250b": {
        "0": {
            "left": 1061,
            "top": 631,
            "right": 1140,
            "bottom": 818
        },
        "1": {
            "left": 1057,
            "top": 631,
            "right": 1136,
            "bottom": 819
        },
        "2": {
            "left": 1053,
            "top": 632,
            "right": 1132,
            "bottom": 820
        },
        "3": {
            "left": 1050,
            "top": 632,
            "right": 1126,
            "bottom": 821
        },
        "4": {
            "left": 1046,
            "top": 633,
            "right": 1122,
            "bottom": 822
        },
        "5": {
            "left": 1041,
            "top": 632,
            "right": 1117,
            "bottom": 824
        },
        "6": {
            "left": 1037,
            "top": 633,
            "right": 1113,
            "bottom": 825
        },
        "7": {
            "left": 1033,
            "top": 633,
            "right": 1108,
            "bottom": 826
        },
        "8": {
            "left": 1029,
            "top": 634,
            "right": 1104,
            "bottom": 827
        },
        "9": {
            "left": 1025,
            "top": 634,
            "right": 1101,
            "bottom": 829
        },
        "10": {
            "left": 1020,
            "top": 634,
            "right": 1099,
            "bottom": 831
        },
        "11": {
            "left": 1017,
            "top": 634,
            "right": 1097,
            "bottom": 832
        },
        "12": {
            "left": 1013,
            "top": 634,
            "right": 1094,
            "bottom": 836
        },
        "13": {
            "left": 1009,
            "top": 634,
            "right": 1093,
            "bottom": 838
        },
        "14": {
            "left": 1006,
            "top": 634,
            "right": 1090,
            "bottom": 839
        },
        "15": {
            "left": 1004,
            "top": 634,
            "right": 1089,
            "bottom": 840
        },
        "16": {
            "left": 1001,
            "top": 634,
            "right": 1088,
            "bottom": 843
        },
        "17": {
            "left": 999,
            "top": 634,
            "right": 1086,
            "bottom": 844
        },
        "18": {
            "left": 997,
            "top": 634,
            "right": 1085,
            "bottom": 845
        },
        "19": {
            "left": 995,
            "top": 633,
            "right": 1083,
            "bottom": 847
        },
        "20": {
            "left": 993,
            "top": 633,
            "right": 1081,
            "bottom": 848
        },
        "21": {
            "left": 991,
            "top": 633,
            "right": 1079,
            "bottom": 850
        },
        "22": {
            "left": 989,
            "top": 631,
            "right": 1077,
            "bottom": 850
        },
        "23": {
            "left": 988,
            "top": 631,
            "right": 1076,
            "bottom": 852
        },
        "24": {
            "left": 986,
            "top": 631,
            "right": 1077,
            "bottom": 853
        },
        "25": {
            "left": 985,
            "top": 630,
            "right": 1076,
            "bottom": 853
        },
        "26": {
            "left": 984,
            "top": 629,
            "right": 1075,
            "bottom": 855
        },
        "27": {
            "left": 982,
            "top": 630,
            "right": 1074,
            "bottom": 857
        },
        "28": {
            "left": 980,
            "top": 630,
            "right": 1072,
            "bottom": 858
        },
        "29": {
            "left": 979,
            "top": 629,
            "right": 1072,
            "bottom": 860
        },
        "30": {
            "left": 977,
            "top": 629,
            "right": 1073,
            "bottom": 861
        },
        "31": {
            "left": 977,
            "top": 629,
            "right": 1073,
            "bottom": 863
        },
        "32": {
            "left": 977,
            "top": 627,
            "right": 1074,
            "bottom": 864
        },
        "33": {
            "left": 978,
            "top": 625,
            "right": 1076,
            "bottom": 864
        },
        "34": {
            "left": 978,
            "top": 623,
            "right": 1079,
            "bottom": 863
        },
        "35": {
            "left": 978,
            "top": 619,
            "right": 1080,
            "bottom": 862
        },
        "36": {
            "left": 979,
            "top": 618,
            "right": 1083,
            "bottom": 862
        },
        "37": {
            "left": 977,
            "top": 617,
            "right": 1082,
            "bottom": 862
        },
        "38": {
            "left": 974,
            "top": 616,
            "right": 1081,
            "bottom": 864
        },
        "39": {
            "left": 973,
            "top": 615,
            "right": 1082,
            "bottom": 864
        },
        "40": {
            "left": 972,
            "top": 615,
            "right": 1082,
            "bottom": 865
        },
        "41": {
            "left": 971,
            "top": 614,
            "right": 1084,
            "bottom": 867
        },
        "42": {
            "left": 971,
            "top": 613,
            "right": 1084,
            "bottom": 867
        },
        "43": {
            "left": 971,
            "top": 613,
            "right": 1085,
            "bottom": 869
        },
        "44": {
            "left": 972,
            "top": 613,
            "right": 1086,
            "bottom": 870
        },
        "45": {
            "left": 974,
            "top": 611,
            "right": 1089,
            "bottom": 871
        },
        "46": {
            "left": 975,
            "top": 611,
            "right": 1090,
            "bottom": 872
        },
        "47": {
            "left": 976,
            "top": 611,
            "right": 1094,
            "bottom": 873
        },
        "48": {
            "left": 978,
            "top": 610,
            "right": 1096,
            "bottom": 876
        },
        "49": {
            "left": 979,
            "top": 609,
            "right": 1098,
            "bottom": 876
        },
        "50": {
            "left": 979,
            "top": 607,
            "right": 1098,
            "bottom": 877
        },
        "51": {
            "left": 980,
            "top": 607,
            "right": 1100,
            "bottom": 878
        },
        "52": {
            "left": 980,
            "top": 606,
            "right": 1100,
            "bottom": 879
        },
        "53": {
            "left": 980,
            "top": 605,
            "right": 1102,
            "bottom": 879
        },
        "54": {
            "left": 981,
            "top": 604,
            "right": 1103,
            "bottom": 882
        },
        "55": {
            "left": 981,
            "top": 603,
            "right": 1103,
            "bottom": 882
        },
        "56": {
            "left": 982,
            "top": 602,
            "right": 1106,
            "bottom": 885
        },
        "57": {
            "left": 984,
            "top": 602,
            "right": 1108,
            "bottom": 886
        },
        "58": {
            "left": 986,
            "top": 602,
            "right": 1112,
            "bottom": 890
        },
        "59": {
            "left": 988,
            "top": 602,
            "right": 1114,
            "bottom": 891
        },
        "60": {
            "left": 990,
            "top": 601,
            "right": 1117,
            "bottom": 894
        },
        "61": {
            "left": 992,
            "top": 601,
            "right": 1119,
            "bottom": 897
        },
        "62": {
            "left": 995,
            "top": 600,
            "right": 1122,
            "bottom": 899
        },
        "63": {
            "left": 996,
            "top": 598,
            "right": 1126,
            "bottom": 899
        },
        "64": {
            "left": 999,
            "top": 595,
            "right": 1129,
            "bottom": 900
        },
        "65": {
            "left": 1001,
            "top": 593,
            "right": 1131,
            "bottom": 901
        },
        "66": {
            "left": 1004,
            "top": 591,
            "right": 1134,
            "bottom": 903
        },
        "67": {
            "left": 1006,
            "top": 589,
            "right": 1137,
            "bottom": 902
        },
        "68": {
            "left": 1009,
            "top": 587,
            "right": 1140,
            "bottom": 904
        },
        "69": {
            "left": 1012,
            "top": 585,
            "right": 1144,
            "bottom": 906
        },
        "70": {
            "left": 1014,
            "top": 583,
            "right": 1146,
            "bottom": 906
        },
        "71": {
            "left": 1015,
            "top": 581,
            "right": 1150,
            "bottom": 906
        },
        "72": {
            "left": 1017,
            "top": 579,
            "right": 1152,
            "bottom": 907
        },
        "73": {
            "left": 1020,
            "top": 576,
            "right": 1156,
            "bottom": 908
        },
        "74": {
            "left": 1022,
            "top": 575,
            "right": 1159,
            "bottom": 910
        },
        "75": {
            "left": 1025,
            "top": 574,
            "right": 1162,
            "bottom": 913
        },
        "76": {
            "left": 1028,
            "top": 573,
            "right": 1167,
            "bottom": 914
        },
        "77": {
            "left": 1031,
            "top": 572,
            "right": 1172,
            "bottom": 917
        },
        "78": {
            "left": 1034,
            "top": 571,
            "right": 1177,
            "bottom": 920
        },
        "79": {
            "left": 1037,
            "top": 571,
            "right": 1181,
            "bottom": 923
        },
        "80": {
            "left": 1040,
            "top": 569,
            "right": 1184,
            "bottom": 925
        },
        "81": {
            "left": 1043,
            "top": 569,
            "right": 1189,
            "bottom": 927
        },
        "82": {
            "left": 1046,
            "top": 568,
            "right": 1194,
            "bottom": 930
        },
        "83": {
            "left": 1049,
            "top": 566,
            "right": 1198,
            "bottom": 932
        },
        "84": {
            "left": 1051,
            "top": 566,
            "right": 1203,
            "bottom": 935
        },
        "85": {
            "left": 1054,
            "top": 565,
            "right": 1207,
            "bottom": 938
        },
        "86": {
            "left": 1057,
            "top": 563,
            "right": 1211,
            "bottom": 941
        },
        "87": {
            "left": 1060,
            "top": 563,
            "right": 1216,
            "bottom": 943
        },
        "88": {
            "left": 1062,
            "top": 562,
            "right": 1220,
            "bottom": 946
        },
        "89": {
            "left": 1065,
            "top": 560,
            "right": 1224,
            "bottom": 948
        },
        "90": {
            "left": 1068,
            "top": 560,
            "right": 1231,
            "bottom": 952
        },
        "91": {
            "left": 1071,
            "top": 559,
            "right": 1236,
            "bottom": 955
        },
        "92": {
            "left": 1074,
            "top": 558,
            "right": 1240,
            "bottom": 958
        },
        "93": {
            "left": 1076,
            "top": 558,
            "right": 1246,
            "bottom": 961
        },
        "94": {
            "left": 1080,
            "top": 557,
            "right": 1251,
            "bottom": 963
        },
        "95": {
            "left": 1082,
            "top": 557,
            "right": 1257,
            "bottom": 966
        },
        "96": {
            "left": 1085,
            "top": 556,
            "right": 1261,
            "bottom": 969
        },
        "97": {
            "left": 1089,
            "top": 556,
            "right": 1267,
            "bottom": 974
        },
        "98": {
            "left": 1091,
            "top": 555,
            "right": 1271,
            "bottom": 977
        },
        "99": {
            "left": 1095,
            "top": 555,
            "right": 1277,
            "bottom": 981
        },
        "100": {
            "left": 1099,
            "top": 554,
            "right": 1282,
            "bottom": 984
        },
        "101": {
            "left": 1101,
            "top": 554,
            "right": 1286,
            "bottom": 989
        },
        "102": {
            "left": 1105,
            "top": 553,
            "right": 1292,
            "bottom": 993
        },
        "103": {
            "left": 1109,
            "top": 553,
            "right": 1297,
            "bottom": 996
        },
        "104": {
            "left": 1112,
            "top": 553,
            "right": 1301,
            "bottom": 1001
        },
        "105": {
            "left": 1115,
            "top": 552,
            "right": 1307,
            "bottom": 1005
        },
        "106": {
            "left": 1119,
            "top": 551,
            "right": 1312,
            "bottom": 1008
        },
        "107": {
            "left": 1123,
            "top": 551,
            "right": 1318,
            "bottom": 1013
        },
        "108": {
            "left": 1126,
            "top": 550,
            "right": 1323,
            "bottom": 1018
        },
        "109": {
            "left": 1129,
            "top": 550,
            "right": 1327,
            "bottom": 1020
        },
        "110": {
            "left": 1132,
            "top": 550,
            "right": 1334,
            "bottom": 1025
        },
        "111": {
            "left": 1136,
            "top": 549,
            "right": 1340,
            "bottom": 1028
        },
        "112": {
            "left": 1140,
            "top": 549,
            "right": 1345,
            "bottom": 1033
        },
        "113": {
            "left": 1144,
            "top": 549,
            "right": 1350,
            "bottom": 1036
        },
        "114": {
            "left": 1147,
            "top": 548,
            "right": 1357,
            "bottom": 1040
        },
        "115": {
            "left": 1151,
            "top": 548,
            "right": 1362,
            "bottom": 1044
        },
        "116": {
            "left": 1153,
            "top": 548,
            "right": 1367,
            "bottom": 1047
        },
        "117": {
            "left": 1157,
            "top": 547,
            "right": 1372,
            "bottom": 1051
        },
        "118": {
            "left": 1161,
            "top": 547,
            "right": 1378,
            "bottom": 1055
        },
        "119": {
            "left": 1164,
            "top": 547,
            "right": 1385,
            "bottom": 1057
        },
        "120": {
            "left": 1168,
            "top": 546,
            "right": 1390,
            "bottom": 1060
        },
        "121": {
            "left": 1172,
            "top": 545,
            "right": 1395,
            "bottom": 1065
        },
        "122": {
            "left": 1174,
            "top": 544,
            "right": 1400,
            "bottom": 1067
        },
        "123": {
            "left": 1178,
            "top": 545,
            "right": 1405,
            "bottom": 1072
        },
        "124": {
            "left": 1182,
            "top": 544,
            "right": 1410,
            "bottom": 1075
        },
        "125": {
            "left": 1185,
            "top": 543,
            "right": 1416,
            "bottom": 1078
        },
        "126": {
            "left": 1189,
            "top": 542,
            "right": 1421,
            "bottom": 1080
        },
        "127": {
            "left": 1193,
            "top": 542,
            "right": 1427,
            "bottom": 1080
        },
        "128": {
            "left": 1196,
            "top": 541,
            "right": 1432,
            "bottom": 1080
        },
        "129": {
            "left": 1201,
            "top": 540,
            "right": 1437,
            "bottom": 1080
        },
        "130": {
            "left": 1205,
            "top": 538,
            "right": 1441,
            "bottom": 1080
        },
        "131": {
            "left": 1209,
            "top": 537,
            "right": 1446,
            "bottom": 1080
        },
        "132": {
            "left": 1213,
            "top": 536,
            "right": 1452,
            "bottom": 1080
        },
        "133": {
            "left": 1218,
            "top": 534,
            "right": 1457,
            "bottom": 1080
        },
        "134": {
            "left": 1222,
            "top": 533,
            "right": 1462,
            "bottom": 1080
        },
        "135": {
            "left": 1225,
            "top": 532,
            "right": 1468,
            "bottom": 1080
        },
        "136": {
            "left": 1229,
            "top": 530,
            "right": 1473,
            "bottom": 1080
        },
        "137": {
            "left": 1232,
            "top": 529,
            "right": 1477,
            "bottom": 1080
        },
        "138": {
            "left": 1235,
            "top": 527,
            "right": 1483,
            "bottom": 1080
        },
        "139": {
            "left": 1239,
            "top": 526,
            "right": 1488,
            "bottom": 1080
        },
        "140": {
            "left": 1241,
            "top": 525,
            "right": 1494,
            "bottom": 1080
        },
        "141": {
            "left": 1244,
            "top": 523,
            "right": 1500,
            "bottom": 1080
        },
        "142": {
            "left": 1246,
            "top": 522,
            "right": 1506,
            "bottom": 1080
        },
        "143": {
            "left": 1249,
            "top": 520,
            "right": 1511,
            "bottom": 1080
        },
        "144": {
            "left": 1251,
            "top": 519,
            "right": 1517,
            "bottom": 1080
        },
        "145": {
            "left": 1254,
            "top": 518,
            "right": 1521,
            "bottom": 1080
        },
        "146": {
            "left": 1256,
            "top": 516,
            "right": 1527,
            "bottom": 1080
        },
        "147": {
            "left": 1259,
            "top": 516,
            "right": 1532,
            "bottom": 1080
        },
        "148": {
            "left": 1261,
            "top": 514,
            "right": 1535,
            "bottom": 1080
        },
        "149": {
            "left": 1263,
            "top": 514,
            "right": 1539,
            "bottom": 1080
        },
        "150": {
            "left": 1266,
            "top": 512,
            "right": 1544,
            "bottom": 1080
        },
        "151": {
            "left": 1269,
            "top": 512,
            "right": 1548,
            "bottom": 1080
        },
        "152": {
            "left": 1271,
            "top": 511,
            "right": 1553,
            "bottom": 1080
        },
        "153": {
            "left": 1274,
            "top": 510,
            "right": 1557,
            "bottom": 1080
        },
        "154": {
            "left": 1276,
            "top": 509,
            "right": 1560,
            "bottom": 1080
        },
        "155": {
            "left": 1279,
            "top": 509,
            "right": 1563,
            "bottom": 1080
        },
        "156": {
            "left": 1282,
            "top": 508,
            "right": 1566,
            "bottom": 1080
        },
        "157": {
            "left": 1285,
            "top": 508,
            "right": 1569,
            "bottom": 1080
        },
        "158": {
            "left": 1288,
            "top": 507,
            "right": 1572,
            "bottom": 1080
        },
        "159": {
            "left": 1291,
            "top": 507,
            "right": 1575,
            "bottom": 1080
        },
        "160": {
            "left": 1289,
            "top": 506,
            "right": 1576,
            "bottom": 1080
        },
        "161": {
            "left": 1288,
            "top": 505,
            "right": 1576,
            "bottom": 1080
        },
        "162": {
            "left": 1288,
            "top": 504,
            "right": 1576,
            "bottom": 1080
        },
        "163": {
            "left": 1287,
            "top": 504,
            "right": 1576,
            "bottom": 1080
        },
        "164": {
            "left": 1286,
            "top": 503,
            "right": 1577,
            "bottom": 1080
        },
        "165": {
            "left": 1284,
            "top": 502,
            "right": 1577,
            "bottom": 1080
        },
        "166": {
            "left": 1283,
            "top": 501,
            "right": 1578,
            "bottom": 1080
        },
        "167": {
            "left": 1283,
            "top": 501,
            "right": 1578,
            "bottom": 1080
        },
        "168": {
            "left": 1282,
            "top": 499,
            "right": 1578,
            "bottom": 1080
        },
        "169": {
            "left": 1280,
            "top": 499,
            "right": 1579,
            "bottom": 1080
        },
        "170": {
            "left": 1277,
            "top": 500,
            "right": 1573,
            "bottom": 1080
        },
        "171": {
            "left": 1273,
            "top": 502,
            "right": 1569,
            "bottom": 1080
        },
        "172": {
            "left": 1270,
            "top": 503,
            "right": 1565,
            "bottom": 1080
        },
        "173": {
            "left": 1266,
            "top": 506,
            "right": 1561,
            "bottom": 1080
        },
        "174": {
            "left": 1262,
            "top": 507,
            "right": 1555,
            "bottom": 1080
        },
        "175": {
            "left": 1257,
            "top": 507,
            "right": 1553,
            "bottom": 1080
        },
        "176": {
            "left": 1250,
            "top": 507,
            "right": 1549,
            "bottom": 1080
        },
        "177": {
            "left": 1245,
            "top": 509,
            "right": 1546,
            "bottom": 1080
        },
        "178": {
            "left": 1238,
            "top": 509,
            "right": 1542,
            "bottom": 1080
        },
        "179": {
            "left": 1233,
            "top": 509,
            "right": 1539,
            "bottom": 1080
        },
        "180": {
            "left": 1215,
            "top": 513,
            "right": 1536,
            "bottom": 1080
        },
        "181": {
            "left": 1198,
            "top": 516,
            "right": 1532,
            "bottom": 1080
        },
        "182": {
            "left": 1181,
            "top": 519,
            "right": 1530,
            "bottom": 1080
        },
        "183": {
            "left": 1164,
            "top": 522,
            "right": 1526,
            "bottom": 1080
        },
        "184": {
            "left": 1147,
            "top": 525,
            "right": 1522,
            "bottom": 1080
        },
        "185": {
            "left": 1146,
            "top": 527,
            "right": 1513,
            "bottom": 1080
        },
        "186": {
            "left": 1146,
            "top": 528,
            "right": 1504,
            "bottom": 1080
        },
        "187": {
            "left": 1146,
            "top": 528,
            "right": 1498,
            "bottom": 1080
        },
        "188": {
            "left": 1145,
            "top": 530,
            "right": 1489,
            "bottom": 1080
        },
        "189": {
            "left": 1144,
            "top": 529,
            "right": 1479,
            "bottom": 1080
        },
        "190": {
            "left": 1141,
            "top": 529,
            "right": 1466,
            "bottom": 1080
        },
        "191": {
            "left": 1136,
            "top": 529,
            "right": 1448,
            "bottom": 1080
        },
        "192": {
            "left": 1128,
            "top": 528,
            "right": 1429,
            "bottom": 1080
        },
        "193": {
            "left": 1119,
            "top": 528,
            "right": 1415,
            "bottom": 1080
        },
        "194": {
            "left": 1102,
            "top": 529,
            "right": 1402,
            "bottom": 1080
        },
        "195": {
            "left": 1086,
            "top": 529,
            "right": 1392,
            "bottom": 1080
        },
        "196": {
            "left": 1069,
            "top": 529,
            "right": 1382,
            "bottom": 1080
        },
        "197": {
            "left": 1050,
            "top": 529,
            "right": 1372,
            "bottom": 1080
        },
        "198": {
            "left": 1032,
            "top": 529,
            "right": 1364,
            "bottom": 1080
        },
        "199": {
            "left": 1017,
            "top": 529,
            "right": 1358,
            "bottom": 1080
        },
        "200": {
            "left": 1004,
            "top": 534,
            "right": 1360,
            "bottom": 1080
        },
        "201": {
            "left": 993,
            "top": 536,
            "right": 1362,
            "bottom": 1080
        },
        "202": {
            "left": 982,
            "top": 537,
            "right": 1360,
            "bottom": 1080
        },
        "203": {
            "left": 973,
            "top": 531,
            "right": 1359,
            "bottom": 1080
        },
        "204": {
            "left": 963,
            "top": 525,
            "right": 1354,
            "bottom": 1080
        },
        "205": {
            "left": 968,
            "top": 524,
            "right": 1320,
            "bottom": 1080
        },
        "206": {
            "left": 968,
            "top": 522,
            "right": 1291,
            "bottom": 1080
        },
        "207": {
            "left": 963,
            "top": 522,
            "right": 1268,
            "bottom": 1080
        },
        "208": {
            "left": 956,
            "top": 521,
            "right": 1255,
            "bottom": 1080
        },
        "209": {
            "left": 944,
            "top": 521,
            "right": 1245,
            "bottom": 1080
        },
        "210": {
            "left": 925,
            "top": 521,
            "right": 1237,
            "bottom": 1080
        },
        "211": {
            "left": 905,
            "top": 522,
            "right": 1227,
            "bottom": 1080
        },
        "212": {
            "left": 898,
            "top": 522,
            "right": 1211,
            "bottom": 1080
        },
        "213": {
            "left": 886,
            "top": 522,
            "right": 1196,
            "bottom": 1080
        },
        "214": {
            "left": 875,
            "top": 523,
            "right": 1183,
            "bottom": 1080
        },
        "215": {
            "left": 859,
            "top": 524,
            "right": 1174,
            "bottom": 1080
        },
        "216": {
            "left": 841,
            "top": 530,
            "right": 1168,
            "bottom": 1080
        },
        "217": {
            "left": 823,
            "top": 535,
            "right": 1163,
            "bottom": 1080
        },
        "218": {
            "left": 806,
            "top": 537,
            "right": 1151,
            "bottom": 1080
        },
        "219": {
            "left": 791,
            "top": 536,
            "right": 1135,
            "bottom": 1080
        },
        "220": {
            "left": 778,
            "top": 530,
            "right": 1117,
            "bottom": 1080
        },
        "221": {
            "left": 764,
            "top": 523,
            "right": 1096,
            "bottom": 1080
        },
        "222": {
            "left": 750,
            "top": 516,
            "right": 1077,
            "bottom": 1080
        },
        "223": {
            "left": 735,
            "top": 510,
            "right": 1057,
            "bottom": 1080
        },
        "224": {
            "left": 717,
            "top": 507,
            "right": 1035,
            "bottom": 1080
        },
        "225": {
            "left": 697,
            "top": 507,
            "right": 1025,
            "bottom": 1080
        },
        "226": {
            "left": 678,
            "top": 508,
            "right": 1017,
            "bottom": 1080
        },
        "227": {
            "left": 659,
            "top": 508,
            "right": 1006,
            "bottom": 1080
        },
        "228": {
            "left": 641,
            "top": 508,
            "right": 995,
            "bottom": 1080
        },
        "229": {
            "left": 624,
            "top": 509,
            "right": 986,
            "bottom": 1080
        },
        "230": {
            "left": 607,
            "top": 512,
            "right": 978,
            "bottom": 1080
        },
        "231": {
            "left": 591,
            "top": 517,
            "right": 969,
            "bottom": 1080
        },
        "232": {
            "left": 575,
            "top": 521,
            "right": 959,
            "bottom": 1080
        },
        "233": {
            "left": 558,
            "top": 525,
            "right": 948,
            "bottom": 1080
        },
        "234": {
            "left": 542,
            "top": 526,
            "right": 933,
            "bottom": 1080
        },
        "235": {
            "left": 525,
            "top": 526,
            "right": 915,
            "bottom": 1080
        },
        "236": {
            "left": 508,
            "top": 525,
            "right": 892,
            "bottom": 1080
        },
        "237": {
            "left": 491,
            "top": 523,
            "right": 869,
            "bottom": 1080
        },
        "238": {
            "left": 475,
            "top": 519,
            "right": 844,
            "bottom": 1080
        },
        "239": {
            "left": 458,
            "top": 515,
            "right": 816,
            "bottom": 1080
        },
        "240": {
            "left": 439,
            "top": 514,
            "right": 796,
            "bottom": 1080
        },
        "241": {
            "left": 421,
            "top": 514,
            "right": 777,
            "bottom": 1080
        },
        "242": {
            "left": 403,
            "top": 515,
            "right": 759,
            "bottom": 1080
        },
        "243": {
            "left": 386,
            "top": 516,
            "right": 742,
            "bottom": 1080
        },
        "244": {
            "left": 370,
            "top": 516,
            "right": 726,
            "bottom": 1080
        },
        "245": {
            "left": 355,
            "top": 517,
            "right": 711,
            "bottom": 1080
        },
        "246": {
            "left": 339,
            "top": 519,
            "right": 706,
            "bottom": 1080
        },
        "247": {
            "left": 320,
            "top": 521,
            "right": 716,
            "bottom": 1080
        },
        "248": {
            "left": 302,
            "top": 524,
            "right": 725,
            "bottom": 1080
        },
        "249": {
            "left": 286,
            "top": 525,
            "right": 722,
            "bottom": 1080
        },
        "250": {
            "left": 280,
            "top": 519,
            "right": 677,
            "bottom": 1080
        },
        "251": {
            "left": 272,
            "top": 514,
            "right": 641,
            "bottom": 1080
        },
        "252": {
            "left": 262,
            "top": 511,
            "right": 607,
            "bottom": 1080
        },
        "253": {
            "left": 249,
            "top": 507,
            "right": 576,
            "bottom": 1080
        },
        "254": {
            "left": 235,
            "top": 504,
            "right": 553,
            "bottom": 1080
        },
        "255": {
            "left": 214,
            "top": 504,
            "right": 535,
            "bottom": 1080
        },
        "256": {
            "left": 195,
            "top": 503,
            "right": 520,
            "bottom": 1080
        },
        "257": {
            "left": 176,
            "top": 503,
            "right": 506,
            "bottom": 1080
        },
        "258": {
            "left": 157,
            "top": 502,
            "right": 495,
            "bottom": 1080
        },
        "259": {
            "left": 138,
            "top": 503,
            "right": 494,
            "bottom": 1080
        },
        "260": {
            "left": 118,
            "top": 504,
            "right": 502,
            "bottom": 1080
        },
        "261": {
            "left": 99,
            "top": 504,
            "right": 512,
            "bottom": 1080
        },
        "262": {
            "left": 84,
            "top": 505,
            "right": 509,
            "bottom": 1080
        },
        "263": {
            "left": 76,
            "top": 504,
            "right": 489,
            "bottom": 1080
        },
        "264": {
            "left": 70,
            "top": 502,
            "right": 458,
            "bottom": 1080
        },
        "265": {
            "left": 64,
            "top": 500,
            "right": 430,
            "bottom": 1080
        },
        "266": {
            "left": 55,
            "top": 498,
            "right": 407,
            "bottom": 1080
        },
        "267": {
            "left": 44,
            "top": 495,
            "right": 384,
            "bottom": 1080
        },
        "268": {
            "left": 32,
            "top": 490,
            "right": 362,
            "bottom": 1080
        },
        "269": {
            "left": 17,
            "top": 485,
            "right": 340,
            "bottom": 1080
        },
        "270": {
            "left": 17,
            "top": 484,
            "right": 325,
            "bottom": 1080
        },
        "271": {
            "left": 8,
            "top": 484,
            "right": 312,
            "bottom": 1080
        },
        "272": {
            "left": 0,
            "top": 484,
            "right": 299,
            "bottom": 1080
        },
        "273": {
            "left": 0,
            "top": 489,
            "right": 293,
            "bottom": 1080
        },
        "274": {
            "left": 0,
            "top": 495,
            "right": 296,
            "bottom": 1080
        },
        "275": {
            "left": 0,
            "top": 493,
            "right": 292,
            "bottom": 1080
        },
        "276": {
            "left": 0,
            "top": 489,
            "right": 279,
            "bottom": 1080
        },
        "277": {
            "left": 0,
            "top": 485,
            "right": 262,
            "bottom": 1080
        },
        "278": {
            "left": 0,
            "top": 483,
            "right": 244,
            "bottom": 1080
        },
        "279": {
            "left": 0,
            "top": 483,
            "right": 226,
            "bottom": 1080
        },
        "280": {
            "left": 0,
            "top": 483,
            "right": 202,
            "bottom": 1080
        },
        "281": {
            "left": 0,
            "top": 484,
            "right": 175,
            "bottom": 1080
        },
        "282": {
            "left": 0,
            "top": 486,
            "right": 145,
            "bottom": 1080
        },
        "283": {
            "left": 0,
            "top": 488,
            "right": 111,
            "bottom": 1080
        },
        "284": {
            "left": 0,
            "top": 491,
            "right": 76,
            "bottom": 1080
        },
        "285": {
            "left": 0,
            "top": 494,
            "right": 63,
            "bottom": 1080
        },
        "286": {
            "left": 0,
            "top": 511,
            "right": 55,
            "bottom": 1080
        },
        "287": {
            "left": 0,
            "top": 495,
            "right": 48,
            "bottom": 1080
        }
    }
}