{
    "0_119_695b": {
        "0": {
            "left": 1084,
            "top": 540,
            "right": 1147,
            "bottom": 676
        },
        "1": {
            "left": 1086,
            "top": 540,
            "right": 1149,
            "bottom": 676
        },
        "2": {
            "left": 1088,
            "top": 541,
            "right": 1151,
            "bottom": 678
        },
        "3": {
            "left": 1090,
            "top": 541,
            "right": 1153,
            "bottom": 678
        },
        "4": {
            "left": 1092,
            "top": 541,
            "right": 1155,
            "bottom": 680
        },
        "5": {
            "left": 1093,
            "top": 542,
            "right": 1155,
            "bottom": 681
        },
        "6": {
            "left": 1095,
            "top": 541,
            "right": 1157,
            "bottom": 682
        },
        "7": {
            "left": 1097,
            "top": 541,
            "right": 1159,
            "bottom": 682
        },
        "8": {
            "left": 1099,
            "top": 542,
            "right": 1161,
            "bottom": 685
        },
        "9": {
            "left": 1101,
            "top": 542,
            "right": 1163,
            "bottom": 685
        },
        "10": {
            "left": 1104,
            "top": 542,
            "right": 1163,
            "bottom": 686
        },
        "11": {
            "left": 1105,
            "top": 541,
            "right": 1163,
            "bottom": 687
        },
        "12": {
            "left": 1107,
            "top": 542,
            "right": 1165,
            "bottom": 691
        },
        "13": {
            "left": 1108,
            "top": 541,
            "right": 1165,
            "bottom": 693
        },
        "14": {
            "left": 1111,
            "top": 541,
            "right": 1165,
            "bottom": 694
        },
        "15": {
            "left": 1113,
            "top": 541,
            "right": 1167,
            "bottom": 694
        },
        "16": {
            "left": 1116,
            "top": 542,
            "right": 1170,
            "bottom": 696
        },
        "17": {
            "left": 1118,
            "top": 542,
            "right": 1172,
            "bottom": 696
        },
        "18": {
            "left": 1121,
            "top": 543,
            "right": 1175,
            "bottom": 699
        },
        "19": {
            "left": 1123,
            "top": 543,
            "right": 1177,
            "bottom": 699
        },
        "20": {
            "left": 1124,
            "top": 540,
            "right": 1181,
            "bottom": 699
        },
        "21": {
            "left": 1127,
            "top": 537,
            "right": 1184,
            "bottom": 700
        },
        "22": {
            "left": 1129,
            "top": 533,
            "right": 1187,
            "bottom": 702
        },
        "23": {
            "left": 1132,
            "top": 531,
            "right": 1190,
            "bottom": 702
        },
        "24": {
            "left": 1134,
            "top": 528,
            "right": 1193,
            "bottom": 703
        },
        "25": {
            "left": 1136,
            "top": 526,
            "right": 1195,
            "bottom": 704
        },
        "26": {
            "left": 1138,
            "top": 523,
            "right": 1200,
            "bottom": 705
        },
        "27": {
            "left": 1140,
            "top": 519,
            "right": 1202,
            "bottom": 706
        },
        "28": {
            "left": 1143,
            "top": 517,
            "right": 1206,
            "bottom": 706
        },
        "29": {
            "left": 1145,
            "top": 514,
            "right": 1208,
            "bottom": 707
        },
        "30": {
            "left": 1147,
            "top": 514,
            "right": 1209,
            "bottom": 711
        },
        "31": {
            "left": 1148,
            "top": 515,
            "right": 1210,
            "bottom": 715
        },
        "32": {
            "left": 1151,
            "top": 514,
            "right": 1210,
            "bottom": 719
        },
        "33": {
            "left": 1152,
            "top": 514,
            "right": 1211,
            "bottom": 723
        },
        "34": {
            "left": 1154,
            "top": 515,
            "right": 1212,
            "bottom": 726
        },
        "35": {
            "left": 1153,
            "top": 513,
            "right": 1216,
            "bottom": 728
        },
        "36": {
            "left": 1153,
            "top": 511,
            "right": 1221,
            "bottom": 730
        },
        "37": {
            "left": 1152,
            "top": 511,
            "right": 1227,
            "bottom": 732
        },
        "38": {
            "left": 1152,
            "top": 510,
            "right": 1232,
            "bottom": 733
        },
        "39": {
            "left": 1151,
            "top": 508,
            "right": 1236,
            "bottom": 735
        },
        "40": {
            "left": 1152,
            "top": 504,
            "right": 1240,
            "bottom": 736
        },
        "41": {
            "left": 1152,
            "top": 499,
            "right": 1244,
            "bottom": 735
        },
        "42": {
            "left": 1153,
            "top": 496,
            "right": 1246,
            "bottom": 736
        },
        "43": {
            "left": 1153,
            "top": 491,
            "right": 1250,
            "bottom": 735
        },
        "44": {
            "left": 1153,
            "top": 487,
            "right": 1254,
            "bottom": 736
        },
        "45": {
            "left": 1156,
            "top": 484,
            "right": 1257,
            "bottom": 738
        },
        "46": {
            "left": 1160,
            "top": 482,
            "right": 1261,
            "bottom": 739
        },
        "47": {
            "left": 1163,
            "top": 479,
            "right": 1264,
            "bottom": 741
        },
        "48": {
            "left": 1167,
            "top": 476,
            "right": 1268,
            "bottom": 742
        },
        "49": {
            "left": 1170,
            "top": 473,
            "right": 1271,
            "bottom": 744
        },
        "50": {
            "left": 1174,
            "top": 473,
            "right": 1278,
            "bottom": 749
        },
        "51": {
            "left": 1177,
            "top": 473,
            "right": 1282,
            "bottom": 755
        },
        "52": {
            "left": 1180,
            "top": 474,
            "right": 1289,
            "bottom": 761
        },
        "53": {
            "left": 1183,
            "top": 475,
            "right": 1293,
            "bottom": 766
        },
        "54": {
            "left": 1186,
            "top": 475,
            "right": 1300,
            "bottom": 771
        },
        "55": {
            "left": 1190,
            "top": 476,
            "right": 1303,
            "bottom": 776
        },
        "56": {
            "left": 1194,
            "top": 477,
            "right": 1307,
            "bottom": 781
        },
        "57": {
            "left": 1200,
            "top": 478,
            "right": 1310,
            "bottom": 786
        },
        "58": {
            "left": 1204,
            "top": 479,
            "right": 1314,
            "bottom": 791
        },
        "59": {
            "left": 1208,
            "top": 480,
            "right": 1317,
            "bottom": 795
        },
        "60": {
            "left": 1213,
            "top": 477,
            "right": 1320,
            "bottom": 799
        },
        "61": {
            "left": 1218,
            "top": 474,
            "right": 1323,
            "bottom": 801
        },
        "62": {
            "left": 1223,
            "top": 470,
            "right": 1327,
            "bottom": 804
        },
        "63": {
            "left": 1227,
            "top": 467,
            "right": 1329,
            "bottom": 806
        },
        "64": {
            "left": 1232,
            "top": 464,
            "right": 1333,
            "bottom": 809
        },
        "65": {
            "left": 1236,
            "top": 460,
            "right": 1340,
            "bottom": 811
        },
        "66": {
            "left": 1240,
            "top": 457,
            "right": 1345,
            "bottom": 814
        },
        "67": {
            "left": 1243,
            "top": 453,
            "right": 1352,
            "bottom": 815
        },
        "68": {
            "left": 1247,
            "top": 450,
            "right": 1357,
            "bottom": 819
        },
        "69": {
            "left": 1250,
            "top": 446,
            "right": 1364,
            "bottom": 820
        },
        "70": {
            "left": 1252,
            "top": 442,
            "right": 1371,
            "bottom": 825
        },
        "71": {
            "left": 1254,
            "top": 440,
            "right": 1376,
            "bottom": 831
        },
        "72": {
            "left": 1256,
            "top": 436,
            "right": 1383,
            "bottom": 837
        },
        "73": {
            "left": 1257,
            "top": 434,
            "right": 1388,
            "bottom": 843
        },
        "74": {
            "left": 1259,
            "top": 430,
            "right": 1395,
            "bottom": 848
        },
        "75": {
            "left": 1263,
            "top": 429,
            "right": 1400,
            "bottom": 855
        },
        "76": {
            "left": 1267,
            "top": 427,
            "right": 1406,
            "bottom": 861
        },
        "77": {
            "left": 1271,
            "top": 425,
            "right": 1414,
            "bottom": 867
        },
        "78": {
            "left": 1275,
            "top": 424,
            "right": 1419,
            "bottom": 872
        },
        "79": {
            "left": 1278,
            "top": 422,
            "right": 1424,
            "bottom": 879
        },
        "80": {
            "left": 1277,
            "top": 420,
            "right": 1435,
            "bottom": 884
        },
        "81": {
            "left": 1276,
            "top": 418,
            "right": 1446,
            "bottom": 888
        },
        "82": {
            "left": 1276,
            "top": 417,
            "right": 1456,
            "bottom": 894
        },
        "83": {
            "left": 1275,
            "top": 414,
            "right": 1467,
            "bottom": 898
        },
        "84": {
            "left": 1274,
            "top": 412,
            "right": 1478,
            "bottom": 903
        },
        "85": {
            "left": 1269,
            "top": 411,
            "right": 1488,
            "bottom": 905
        },
        "86": {
            "left": 1264,
            "top": 410,
            "right": 1500,
            "bottom": 909
        },
        "87": {
            "left": 1259,
            "top": 408,
            "right": 1509,
            "bottom": 911
        },
        "88": {
            "left": 1254,
            "top": 407,
            "right": 1521,
            "bottom": 915
        },
        "89": {
            "left": 1249,
            "top": 406,
            "right": 1532,
            "bottom": 916
        },
        "90": {
            "left": 1254,
            "top": 403,
            "right": 1536,
            "bottom": 924
        },
        "91": {
            "left": 1260,
            "top": 401,
            "right": 1539,
            "bottom": 934
        },
        "92": {
            "left": 1264,
            "top": 398,
            "right": 1542,
            "bottom": 941
        },
        "93": {
            "left": 1269,
            "top": 396,
            "right": 1545,
            "bottom": 951
        },
        "94": {
            "left": 1275,
            "top": 393,
            "right": 1549,
            "bottom": 958
        },
        "95": {
            "left": 1281,
            "top": 390,
            "right": 1538,
            "bottom": 962
        },
        "96": {
            "left": 1286,
            "top": 388,
            "right": 1529,
            "bottom": 965
        },
        "97": {
            "left": 1292,
            "top": 385,
            "right": 1518,
            "bottom": 968
        },
        "98": {
            "left": 1298,
            "top": 383,
            "right": 1508,
            "bottom": 971
        },
        "99": {
            "left": 1304,
            "top": 380,
            "right": 1497,
            "bottom": 975
        },
        "100": {
            "left": 1291,
            "top": 379,
            "right": 1502,
            "bottom": 979
        },
        "101": {
            "left": 1277,
            "top": 377,
            "right": 1508,
            "bottom": 982
        },
        "102": {
            "left": 1265,
            "top": 376,
            "right": 1514,
            "bottom": 987
        },
        "103": {
            "left": 1252,
            "top": 374,
            "right": 1519,
            "bottom": 990
        },
        "104": {
            "left": 1238,
            "top": 373,
            "right": 1525,
            "bottom": 994
        },
        "105": {
            "left": 1228,
            "top": 371,
            "right": 1536,
            "bottom": 1000
        },
        "106": {
            "left": 1218,
            "top": 368,
            "right": 1548,
            "bottom": 1006
        },
        "107": {
            "left": 1207,
            "top": 366,
            "right": 1558,
            "bottom": 1012
        },
        "108": {
            "left": 1197,
            "top": 363,
            "right": 1570,
            "bottom": 1018
        },
        "109": {
            "left": 1186,
            "top": 361,
            "right": 1581,
            "bottom": 1024
        },
        "110": {
            "left": 1195,
            "top": 357,
            "right": 1569,
            "bottom": 1029
        },
        "111": {
            "left": 1202,
            "top": 354,
            "right": 1556,
            "bottom": 1033
        },
        "112": {
            "left": 1211,
            "top": 349,
            "right": 1543,
            "bottom": 1036
        },
        "113": {
            "left": 1219,
            "top": 346,
            "right": 1531,
            "bottom": 1041
        },
        "114": {
            "left": 1228,
            "top": 342,
            "right": 1519,
            "bottom": 1046
        },
        "115": {
            "left": 1222,
            "top": 340,
            "right": 1506,
            "bottom": 1052
        },
        "116": {
            "left": 1217,
            "top": 338,
            "right": 1495,
            "bottom": 1056
        },
        "117": {
            "left": 1211,
            "top": 334,
            "right": 1481,
            "bottom": 1062
        },
        "118": {
            "left": 1207,
            "top": 332,
            "right": 1469,
            "bottom": 1066
        },
        "119": {
            "left": 1201,
            "top": 329,
            "right": 1457,
            "bottom": 1072
        },
        "120": {
            "left": 1171,
            "top": 330,
            "right": 1466,
            "bottom": 1074
        },
        "121": {
            "left": 1141,
            "top": 331,
            "right": 1473,
            "bottom": 1077
        },
        "122": {
            "left": 1111,
            "top": 333,
            "right": 1482,
            "bottom": 1079
        },
        "123": {
            "left": 1082,
            "top": 334,
            "right": 1490,
            "bottom": 1080
        },
        "124": {
            "left": 1052,
            "top": 334,
            "right": 1499,
            "bottom": 1080
        },
        "125": {
            "left": 1053,
            "top": 332,
            "right": 1488,
            "bottom": 1080
        },
        "126": {
            "left": 1054,
            "top": 330,
            "right": 1477,
            "bottom": 1080
        },
        "127": {
            "left": 1056,
            "top": 328,
            "right": 1469,
            "bottom": 1080
        },
        "128": {
            "left": 1057,
            "top": 326,
            "right": 1458,
            "bottom": 1080
        },
        "129": {
            "left": 1058,
            "top": 324,
            "right": 1448,
            "bottom": 1080
        },
        "130": {
            "left": 1056,
            "top": 319,
            "right": 1422,
            "bottom": 1080
        },
        "131": {
            "left": 1053,
            "top": 314,
            "right": 1397,
            "bottom": 1080
        },
        "132": {
            "left": 1051,
            "top": 309,
            "right": 1372,
            "bottom": 1080
        },
        "133": {
            "left": 1048,
            "top": 303,
            "right": 1347,
            "bottom": 1080
        },
        "134": {
            "left": 1047,
            "top": 299,
            "right": 1321,
            "bottom": 1080
        },
        "135": {
            "left": 1009,
            "top": 303,
            "right": 1327,
            "bottom": 1080
        },
        "136": {
            "left": 970,
            "top": 305,
            "right": 1332,
            "bottom": 1080
        },
        "137": {
            "left": 932,
            "top": 309,
            "right": 1337,
            "bottom": 1080
        },
        "138": {
            "left": 894,
            "top": 312,
            "right": 1342,
            "bottom": 1080
        },
        "139": {
            "left": 856,
            "top": 316,
            "right": 1348,
            "bottom": 1080
        },
        "140": {
            "left": 861,
            "top": 314,
            "right": 1334,
            "bottom": 1080
        },
        "141": {
            "left": 867,
            "top": 311,
            "right": 1319,
            "bottom": 1080
        },
        "142": {
            "left": 872,
            "top": 309,
            "right": 1302,
            "bottom": 1080
        },
        "143": {
            "left": 878,
            "top": 306,
            "right": 1287,
            "bottom": 1080
        },
        "144": {
            "left": 883,
            "top": 304,
            "right": 1273,
            "bottom": 1080
        },
        "145": {
            "left": 876,
            "top": 303,
            "right": 1245,
            "bottom": 1080
        },
        "146": {
            "left": 868,
            "top": 302,
            "right": 1217,
            "bottom": 1080
        },
        "147": {
            "left": 861,
            "top": 300,
            "right": 1188,
            "bottom": 1080
        },
        "148": {
            "left": 854,
            "top": 298,
            "right": 1160,
            "bottom": 1080
        },
        "149": {
            "left": 846,
            "top": 297,
            "right": 1133,
            "bottom": 1080
        },
        "150": {
            "left": 814,
            "top": 301,
            "right": 1131,
            "bottom": 1080
        },
        "151": {
            "left": 781,
            "top": 304,
            "right": 1128,
            "bottom": 1080
        },
        "152": {
            "left": 748,
            "top": 308,
            "right": 1127,
            "bottom": 1080
        },
        "153": {
            "left": 715,
            "top": 310,
            "right": 1124,
            "bottom": 1080
        },
        "154": {
            "left": 682,
            "top": 314,
            "right": 1122,
            "bottom": 1080
        },
        "155": {
            "left": 677,
            "top": 314,
            "right": 1116,
            "bottom": 1080
        },
        "156": {
            "left": 673,
            "top": 313,
            "right": 1112,
            "bottom": 1080
        },
        "157": {
            "left": 669,
            "top": 312,
            "right": 1105,
            "bottom": 1080
        },
        "158": {
            "left": 665,
            "top": 311,
            "right": 1101,
            "bottom": 1080
        },
        "159": {
            "left": 660,
            "top": 311,
            "right": 1095,
            "bottom": 1080
        },
        "160": {
            "left": 656,
            "top": 309,
            "right": 1056,
            "bottom": 1080
        },
        "161": {
            "left": 652,
            "top": 307,
            "right": 1016,
            "bottom": 1080
        },
        "162": {
            "left": 648,
            "top": 305,
            "right": 978,
            "bottom": 1080
        },
        "163": {
            "left": 643,
            "top": 303,
            "right": 938,
            "bottom": 1080
        },
        "164": {
            "left": 639,
            "top": 301,
            "right": 899,
            "bottom": 1080
        },
        "165": {
            "left": 602,
            "top": 302,
            "right": 901,
            "bottom": 1080
        },
        "166": {
            "left": 566,
            "top": 302,
            "right": 901,
            "bottom": 1080
        },
        "167": {
            "left": 529,
            "top": 303,
            "right": 903,
            "bottom": 1080
        },
        "168": {
            "left": 492,
            "top": 304,
            "right": 904,
            "bottom": 1080
        },
        "169": {
            "left": 455,
            "top": 304,
            "right": 906,
            "bottom": 1080
        },
        "170": {
            "left": 449,
            "top": 307,
            "right": 902,
            "bottom": 1080
        },
        "171": {
            "left": 442,
            "top": 309,
            "right": 899,
            "bottom": 1080
        },
        "172": {
            "left": 435,
            "top": 313,
            "right": 897,
            "bottom": 1080
        },
        "173": {
            "left": 429,
            "top": 316,
            "right": 894,
            "bottom": 1080
        },
        "174": {
            "left": 422,
            "top": 318,
            "right": 891,
            "bottom": 1080
        },
        "175": {
            "left": 419,
            "top": 315,
            "right": 855,
            "bottom": 1080
        },
        "176": {
            "left": 415,
            "top": 312,
            "right": 818,
            "bottom": 1080
        },
        "177": {
            "left": 411,
            "top": 309,
            "right": 782,
            "bottom": 1080
        },
        "178": {
            "left": 407,
            "top": 306,
            "right": 745,
            "bottom": 1080
        },
        "179": {
            "left": 404,
            "top": 303,
            "right": 709,
            "bottom": 1080
        },
        "180": {
            "left": 386,
            "top": 305,
            "right": 696,
            "bottom": 1080
        },
        "181": {
            "left": 368,
            "top": 307,
            "right": 683,
            "bottom": 1080
        },
        "182": {
            "left": 349,
            "top": 310,
            "right": 670,
            "bottom": 1080
        },
        "183": {
            "left": 332,
            "top": 312,
            "right": 657,
            "bottom": 1080
        },
        "184": {
            "left": 314,
            "top": 315,
            "right": 644,
            "bottom": 1080
        },
        "185": {
            "left": 294,
            "top": 317,
            "right": 646,
            "bottom": 1080
        },
        "186": {
            "left": 274,
            "top": 320,
            "right": 648,
            "bottom": 1080
        },
        "187": {
            "left": 253,
            "top": 322,
            "right": 648,
            "bottom": 1080
        },
        "188": {
            "left": 233,
            "top": 325,
            "right": 650,
            "bottom": 1080
        },
        "189": {
            "left": 213,
            "top": 328,
            "right": 652,
            "bottom": 1080
        },
        "190": {
            "left": 209,
            "top": 328,
            "right": 621,
            "bottom": 1080
        },
        "191": {
            "left": 205,
            "top": 328,
            "right": 589,
            "bottom": 1080
        },
        "192": {
            "left": 200,
            "top": 328,
            "right": 558,
            "bottom": 1080
        },
        "193": {
            "left": 195,
            "top": 328,
            "right": 527,
            "bottom": 1080
        },
        "194": {
            "left": 191,
            "top": 328,
            "right": 496,
            "bottom": 1080
        },
        "195": {
            "left": 170,
            "top": 326,
            "right": 483,
            "bottom": 1080
        },
        "196": {
            "left": 147,
            "top": 325,
            "right": 468,
            "bottom": 1080
        },
        "197": {
            "left": 126,
            "top": 323,
            "right": 454,
            "bottom": 1080
        },
        "198": {
            "left": 104,
            "top": 321,
            "right": 439,
            "bottom": 1080
        },
        "199": {
            "left": 82,
            "top": 320,
            "right": 426,
            "bottom": 1080
        },
        "200": {
            "left": 63,
            "top": 323,
            "right": 424,
            "bottom": 1080
        },
        "201": {
            "left": 44,
            "top": 325,
            "right": 423,
            "bottom": 1080
        },
        "202": {
            "left": 26,
            "top": 328,
            "right": 422,
            "bottom": 1080
        },
        "203": {
            "left": 7,
            "top": 330,
            "right": 421,
            "bottom": 1080
        },
        "204": {
            "left": 0,
            "top": 332,
            "right": 416,
            "bottom": 1080
        },
        "205": {
            "left": 0,
            "top": 335,
            "right": 379,
            "bottom": 1080
        },
        "206": {
            "left": 0,
            "top": 337,
            "right": 343,
            "bottom": 1080
        },
        "207": {
            "left": 0,
            "top": 340,
            "right": 309,
            "bottom": 1080
        },
        "208": {
            "left": 0,
            "top": 342,
            "right": 273,
            "bottom": 1080
        },
        "209": {
            "left": 0,
            "top": 344,
            "right": 236,
            "bottom": 1080
        }
    },
    "0_119_694b": {
        "0": {
            "left": 1159,
            "top": 485,
            "right": 1279,
            "bottom": 791
        },
        "1": {
            "left": 1171,
            "top": 482,
            "right": 1293,
            "bottom": 799
        },
        "2": {
            "left": 1182,
            "top": 479,
            "right": 1306,
            "bottom": 807
        },
        "3": {
            "left": 1195,
            "top": 475,
            "right": 1321,
            "bottom": 815
        },
        "4": {
            "left": 1206,
            "top": 476,
            "right": 1308,
            "bottom": 804
        },
        "5": {
            "left": 1210,
            "top": 474,
            "right": 1317,
            "bottom": 813
        },
        "6": {
            "left": 1218,
            "top": 472,
            "right": 1328,
            "bottom": 821
        },
        "7": {
            "left": 1226,
            "top": 470,
            "right": 1341,
            "bottom": 828
        },
        "8": {
            "left": 1236,
            "top": 466,
            "right": 1355,
            "bottom": 837
        },
        "9": {
            "left": 1248,
            "top": 463,
            "right": 1372,
            "bottom": 847
        },
        "10": {
            "left": 1262,
            "top": 460,
            "right": 1389,
            "bottom": 857
        },
        "11": {
            "left": 1275,
            "top": 456,
            "right": 1406,
            "bottom": 869
        },
        "12": {
            "left": 1290,
            "top": 452,
            "right": 1426,
            "bottom": 881
        },
        "13": {
            "left": 1307,
            "top": 448,
            "right": 1446,
            "bottom": 891
        },
        "14": {
            "left": 1323,
            "top": 444,
            "right": 1467,
            "bottom": 902
        },
        "15": {
            "left": 1340,
            "top": 439,
            "right": 1488,
            "bottom": 914
        },
        "16": {
            "left": 1357,
            "top": 434,
            "right": 1510,
            "bottom": 926
        },
        "17": {
            "left": 1378,
            "top": 429,
            "right": 1534,
            "bottom": 939
        },
        "18": {
            "left": 1402,
            "top": 423,
            "right": 1561,
            "bottom": 954
        },
        "19": {
            "left": 1427,
            "top": 416,
            "right": 1592,
            "bottom": 969
        },
        "20": {
            "left": 1436,
            "top": 408,
            "right": 1631,
            "bottom": 986
        },
        "21": {
            "left": 1475,
            "top": 395,
            "right": 1672,
            "bottom": 1006
        },
        "22": {
            "left": 1497,
            "top": 382,
            "right": 1702,
            "bottom": 1025
        },
        "23": {
            "left": 1540,
            "top": 369,
            "right": 1746,
            "bottom": 1046
        },
        "24": {
            "left": 1559,
            "top": 356,
            "right": 1799,
            "bottom": 1065
        },
        "25": {
            "left": 1607,
            "top": 345,
            "right": 1841,
            "bottom": 1080
        },
        "26": {
            "left": 1647,
            "top": 332,
            "right": 1886,
            "bottom": 1080
        },
        "27": {
            "left": 1701,
            "top": 319,
            "right": 1920,
            "bottom": 1080
        },
        "28": {
            "left": 1754,
            "top": 306,
            "right": 1920,
            "bottom": 1080
        },
        "29": {
            "left": 1806,
            "top": 306,
            "right": 1920,
            "bottom": 1080
        }
    }
}